CarlosArturAlencarCruz/processor.v
module Processor (
    input wire clk,
    input wire reset
);
    wire [31:0] PCout_pro, instruction_pro, Rd1_pro, Rd2_pro, SigExt_pro, MuxALU_pro, Add4Out_pro, AdderIn_pro, AdderOut_pro, ALUResult_pro, ReadData_pro, MuxMem_pro,MuxAdderOut_pro, PCin_pro;
    wire [27:0] SLTJumpOut_pro;
    wire [1:0] ALUOp_pro;
    wire [4:0] MuxReg_pro;
    wire [3:0] ALUOperation_pro;
    wire RegWrite_pro, RegDst_pro, ALUSrc_pro, Branch_pro, AndOut_pro, MemRead_pro, MemWrite_pro, MemtoReg_pro, Zero_pro, Jump_pro;

    // Contador de programa
    ProgramCounter PC (
        .clk(clk), 
        .reset(reset), 
        .pc_in(PCin_pro), 
        .pc_out(PCout_pro)
    );

    // Somador do PC
    Add4 PC_Adder (.in(PCout_pro), .out(Add4Out_pro));

    // Memória de instruções
    InstructionMemory Inst_Memory (
        .addr(PCout_pro), 
        .instruction(instruction_pro)
    );

    // Multiplexador do arquivo de resgistradores
    Mux2x1Reg MuxRegFile (
        .A(instruction_pro[20:16]), 
        .B(instruction_pro[15:11]),
        .sel(RegDst_pro),
        .out(MuxReg_pro)
    );

    // Registradores
    RegisterFile Registers (
        .clk(clk),
        .ReadRegister1(instruction_pro[25:21]), 
        .ReadRegister2(instruction_pro[20:16]),  
        .WriteRegister(MuxReg_pro), 
        .WriteData(MuxMem_pro),    
        .RegWrite(RegWrite_pro),             
        .ReadData1(Rd1_pro),    
        .ReadData2(Rd2_pro)
    );

    // Extensor de sinal
    SignalExtend Signal_Ext (
        .in(instruction_pro[15:0]), 
        .out(SigExt_pro)
    );

    // Unidade de Controle
    Control_Unit Control(
        .instruction(instruction_pro[31:26]),
        .RegDst(RegDst_pro), 
        .Jump(Jump_pro), 
        .Branch(Branch_pro), 
        .MemRead(MemRead_pro), 
        .MemWrite(MemWrite_pro),
        .MemtoReg(MemtoReg_pro), 
        .RegWrite(RegWrite_pro), 
        .ALUSrc(ALUSrc_pro), 
        .ALUOp(ALUOp_pro)
    );

    // Unidade de controle da ALU
    ALU_Control ALU_Control(
        .ALUOp(ALUOp_pro),
        .funct(instruction_pro[5:0]),
        .control_out(ALUOperation_pro)
    );

    // Unidade Lógica e Aritmética
    ALU ALU(
        .A(Rd1_pro),
        .B(MuxALU_pro),           
        .ALUOperation(ALUOperation_pro), 
        .ALUResult(ALUResult_pro),   
        .Zero(Zero_pro)     
    );

    // Multiplexador da ALU
    Mux2x1 MuxALU (
        .A(Rd2_pro), 
        .B(SigExt_pro),
        .sel(ALUSrc_pro),
        .out(MuxALU_pro)
    );

    // Somador de 32 bits
    Adder32 Adder32(
        .A(Add4Out_pro),
        .B(AdderIn_pro),
        .sum(AdderOut_pro)
    );

    // Operação de deslocamento à esquerda
    ShiftLeft2 SLT_Adder (
        .in(SigExt_pro),
        .out(AdderIn_pro)
    );

    // Porta AND
    AND_logic AND_Gate ( 
        .branch(Branch_pro),
        .zero(Zero_pro),
        .and_out(AndOut_pro)
    );

    // Multiplexador dos somadores 
    Mux2x1 MuxAdder (
        .A(Add4Out_pro),
        .B(AdderOut_pro),
        .sel(AndOut_pro),
        .out(MuxAdderOut_pro)
    );

    // Memória de Dados
    DataMemory DataMemory (
        .clk(clk),          
        .MemRead(MemRead_pro),
        .MemWrite(MemWrite_pro),
        .address(ALUResult_pro), 
        .writeData(Rd2_pro),
        .readData(ReadData_pro) 
    );

    // Multiplexador da saída de memória
    Mux2x1 MuxMemory (
        .A(ALUResult_pro),
        .B(ReadData_pro),
        .sel(MemtoReg_pro),
        .out(MuxMem_pro)
    );

    // Multiplexador de jump 
    Mux2x1 MuxJump (
        .A(MuxAdderOut_pro),
        .B({Add4Out_pro[31:28], SLTJumpOut_pro}),
        .sel(Jump_pro),
        .out(PCin_pro)
    );
    
    // Deslocamento de 2 bits para calcular endereço do jump
    ShiftLeft2Jump SLT_Jump (
        .in(instruction_pro[25:0]),
        .out(SLTJumpOut_pro)
    );
endmodule



// CONTADOR DE PROGRAMA
module ProgramCounter (
    input wire clk,
    input wire reset,
    input wire [31:0] pc_in,
    output reg [31:0] pc_out
);
    // Lógica do PC: reset ou incrementa
    always @(posedge clk or posedge reset) begin
        if (reset) begin
            // Inicializa o PC no reset
            pc_out <= 32'b0;
        end else begin
            // Atualiza o PC com o próximo endereço
            pc_out <= pc_in;
        end
    end  
endmodule


// SOMADOR DO PC
module Add4(
    input wire [31:0] in,        // Endereço atual do PC
    output wire [31:0] out       // Endereço incrementado
);
    assign out = in + 32'd4;     // Soma 4 ao valor de entrada
endmodule


// MEMÓRIA DE INSTRUÇÕES
module InstructionMemory(
    input wire [31:0] addr,      // Endereço da instrução
    output wire [31:0] instruction // Instrução lida
);

    // Memória de instruções (256 palavras de 32 bits)
    reg [31:0] memory [255:0];

    // Inicialização da memória a partir de um arquivo binário
    initial begin
        $readmemb("codigo.mem", memory);  // Carrega o arquivo binário na memória
    end

    // Leitura combinacional
    assign instruction = memory[addr[9:2]]; // Usa os bits 9:2 para indexar (alinhado em palavras)
endmodule


// MULTIPLEXADOR 2x1
module Mux2x1 (
    input wire[31:0] A, 
    input wire[31:0] B,
    input wire sel,
    output wire[31:0] out
);

    assign out = (sel == 1'b0) ? A : B;
endmodule


// MULTIPLEXADOR DO ARQUIVO DE REGISTRADORES
module Mux2x1Reg (
    input wire[4:0] A, 
    input wire[4:0] B,
    input wire sel,
    output wire[4:0] out
);

    assign out = (sel == 1'b0) ? A : B;
endmodule


// ARQUIVO DE REGISTRADORES
module RegisterFile(
    input wire clk,
    input wire [4:0] ReadRegister1,  // Endereço do registrador para leitura 1
    input wire [4:0] ReadRegister2,  // Endereço do registrador para leitura 2
    input wire [4:0] WriteRegister,  // Endereço do registrador para escrita
    input wire [31:0] WriteData,     // Dados a serem escritos
    input wire RegWrite,             // Habilitação de escrita
    output wire [31:0] ReadData1,    // Dados lidos do registrador 1
    output wire [31:0] ReadData2     // Dados lidos do registrador 2
);

    // Banco de registradores: 32 registradores de 32 bits
    reg [31:0] registers [31:0];

    // Inicialização dos registradores (opcional, apenas para simulação)
    integer i;
    initial begin
        for (i = 0; i < 32; i = i + 1) begin
            registers[i] = 32'b0;  // Inicializa todos com zero
        end
    end

    // Leitura combinacional
    assign ReadData1 = registers[ReadRegister1];
    assign ReadData2 = registers[ReadRegister2];

    // Escrita síncrona
    always @(posedge clk) begin
        if (RegWrite && WriteRegister != 5'b0) begin
            registers[WriteRegister] <= WriteData;  // Escreve no registrador
        end
    end
endmodule


// EXTENSOR DE SINAL
module SignalExtend(
    input wire [15:0] in,         // Campo de 16 bits a ser estendido
    output wire [31:0] out        // Resultado estendido para 32 bits
);

    assign out = {{16{in[15]}}, in}; // Extensão de sinal replicando o bit mais significativo
endmodule


// UNIDADE DE CONTROLE PRINCIPAL
module Control_Unit (
    input wire[31:26] instruction,
    output reg RegDst, 
    output reg Jump, 
    output reg Branch, 
    output reg MemRead, 
    output reg MemWrite,
    output reg MemtoReg, 
    output reg RegWrite, 
    output reg ALUSrc, 
    output reg [1:0]ALUOp
);

    always @(*) begin
        RegDst    = 1'b0;
        ALUSrc    = 1'b0;
        MemtoReg  = 1'b0;
        RegWrite  = 1'b0;
        MemRead   = 1'b0;
        MemWrite  = 1'b0;
        Branch    = 1'b0;
        Jump      = 1'b0;
        ALUOp     = 2'b00;

        case (instruction)
            //I-TYPE
            6'b001000: begin // addi
                RegDst    = 1'b0;
                ALUSrc    = 1'b1;
                MemtoReg  = 1'b0;
                RegWrite  = 1'b1;
                MemRead   = 1'b0;
                MemWrite  = 1'b0;
                Branch    = 1'b0;
                Jump      = 1'b0;
                ALUOp     = 2'b10;
            end

            //R-TYPE
            6'b000000: begin 
                RegDst    = 1'b1;
                ALUSrc    = 1'b0;
                MemtoReg  = 1'b0;
                RegWrite  = 1'b1;
                MemRead   = 1'b0;
                MemWrite  = 1'b0;
                Branch    = 1'b0;
                Jump      = 1'b0;
                ALUOp     = 2'b10;
            end

            //LOAD
            6'b100011: begin 
                RegDst    = 1'b0;
                ALUSrc    = 1'b1;
                MemtoReg  = 1'b1;
                RegWrite  = 1'b1;
                MemRead   = 1'b1;
                MemWrite  = 1'b0;
                Branch    = 1'b0;
                Jump      = 1'b0;
                ALUOp     = 2'b00;
            end

            //STORE
            6'b101011: begin
                RegDst    = 1'b0;
                ALUSrc    = 1'b1;
                MemtoReg  = 1'bX; // Não é relevante
                RegWrite  = 1'b0;
                MemRead   = 1'b0;
                MemWrite  = 1'b1;
                Branch    = 1'b0;
                Jump      = 1'b0;
                ALUOp     = 2'b00;
            end

            //BEQ
            6'b000100: begin 
                RegDst    = 1'b0;
                ALUSrc    = 1'b0;
                MemtoReg  = 1'bX; // Não é relevante
                RegWrite  = 1'b0;
                MemRead   = 1'b0;
                MemWrite  = 1'b0;
                Branch    = 1'b1;
                Jump      = 1'b0;
                ALUOp     = 2'b01;
            end

            //JUMP
            6'b000010: begin
                RegDst    = 1'bX; // Não é relevante
                ALUSrc    = 1'bX; // Não é relevante
                MemtoReg  = 1'bX; // Não é relevante
                RegWrite  = 1'b0;
                MemRead   = 1'b0;
                MemWrite  = 1'b0;
                Branch    = 1'b0;
                Jump      = 1'b1;
                ALUOp     = 2'bXX;
            end
        endcase
    end
endmodule


// ALU
module ALU(
    input wire [31:0] A,           // Operando 1
    input wire [31:0] B,           // Operando 2
    input wire [3:0] ALUOperation, // Código da operação ALU
    output reg [31:0] ALUResult,   // Resultado da ALU
    output wire Zero               // Sinal Zero (ativo quando ALUResult é 0)
);

    // Define o comportamento da ALU
    always @(*) begin
        case (ALUOperation)
            4'b0000: ALUResult = A & B;          // AND
            4'b0001: ALUResult = A | B;          // OR
            4'b0010: ALUResult = A + B;          // Soma
            4'b0110: ALUResult = A - B;          // Subtração
            4'b0111: ALUResult = (A < B) ? 1 : 0; // SLT (Set Less Than)
            4'b1100: ALUResult = ~(A | B);       // NOR
            default: ALUResult = 32'b0;          // Operação inválida
        endcase
    end

    // Define o sinal Zero
    assign Zero = (ALUResult == 32'b0) ? 1'b1 : 1'b0;

endmodule


// UNIDADE DE CONTROLE DA ALU
module ALU_Control (
    input wire[1:0] ALUOp,
    input wire[5:0] funct,
    output reg[3:0] control_out
);

    always @(*) begin
        case (ALUOp)
            2'b00: control_out = 4'b0010; // lw e sw (soma)
            2'b01: control_out = 4'b0110; // beq (subtração)
            2'b10: begin  // Tipo R (definido pelo funct)
                case (funct)
                    6'b100000: control_out = 4'b0010; // add
                    6'b100010: control_out = 4'b0110; // sub
                    6'b100100: control_out = 4'b0000; // and
                    6'b100101: control_out = 4'b0001; // or
                    6'b101010: control_out = 4'b0111; // slt
                    default:   control_out = 4'b0010; // Tipo I
                endcase
            end
            default: control_out = 4'b0010; // Padrão
        endcase
    end
endmodule


// MEMÓRIA DE DADOS
module DataMemory(
    input wire clk,                // Clock
    input wire MemRead,            // Sinal de leitura
    input wire MemWrite,           // Sinal de escrita
    input wire [31:0] address,     // Endereço de memória
    input wire [31:0] writeData,   // Dados a serem escritos
    output wire [31:0] readData    // Dados lidos
);

    // Memória de dados (256 palavras de 32 bits)
    reg [31:0] memory [255:0];

    // Inicializa a memória para simulação (opcional)
    integer i;
    initial begin
        for (i = 0; i < 256; i = i + 1) begin
            memory[i] = 32'b0; // Inicializa com zero
        end
    end

    // Leitura combinacional
    assign readData = (MemRead) ? memory[address[9:2]] : 32'b0;

    // Escrita combinacional
    always @(posedge clk) begin
        if (MemWrite) begin
            memory[address[9:2]] <= writeData; // Escreve na memória
        end
    end
endmodule


// DESLOCAMENTO DE 2 BITS
module ShiftLeft2(
    input wire [31:0] in,          // Entrada de 32 bits
    output wire [31:0] out         // Saída deslocada
);

    assign out = in << 2;          // Desloca à esquerda em 2 bits
endmodule

// SLT JUMP
module ShiftLeft2Jump(
    input wire [25:0] in,          // Entrada de 32 bits
    output wire [27:0] out         // Saída deslocada
);

    assign out = in << 2;          // Desloca à esquerda em 2 bits
endmodule

// SOMADOR DE 32 BITS
module Adder32(
    input wire [31:0] A,           // Operando A
    input wire [31:0] B,           // Operando B
    output wire [31:0] sum         // Resultado da soma
);

    assign sum = A + B;            // Soma A + B
endmodule

// PORTA LÓGICA AND
module AND_logic (
    input wire branch,
    input wire zero,
    output wire and_out
);

    assign and_out = branch & zero;
endmodule

CarlosArturAlencarCruz/processor_tb.v
`include "processor.v"
`timescale 1ps/1ps

module processor_tb;
    // Sinais de entrada
    reg clk;
    reg reset;

    // Instancia o processador MIPS de ciclo único
    Processor uut (
        .clk(clk),
        .reset(reset)
    );
    
    // Gera o clock
    always #5 clk = ~clk;
    
    initial begin
        $dumpfile("processor_sim.vcd");
        $dumpvars(0, processor_tb);

        // Inicializa sinais
        clk = 0;
        reset = 1;
        
        // Aplica reset
        #20;
        reset = 0;
        
        // Executa a simulação por um determinado tempo
        #200;
        
        // Finaliza a simulação
        $finish;
    end
endmodule

CarlosArturAlencarCruz/processor_sim.vcd
$date
	Sun Feb 09 21:35:50 2025
$end
$version
	Icarus Verilog
$end
$timescale
	1ps
$end
$scope module processor_tb $end
$var reg 1 ! clk $end
$var reg 1 " reset $end
$scope module uut $end
$var wire 1 ! clk $end
$var wire 1 " reset $end
$var wire 32 # instruction_pro [31:0] $end
$var wire 1 $ Zero_pro $end
$var wire 32 % SigExt_pro [31:0] $end
$var wire 28 & SLTJumpOut_pro [27:0] $end
$var wire 1 ' RegWrite_pro $end
$var wire 1 ( RegDst_pro $end
$var wire 32 ) ReadData_pro [31:0] $end
$var wire 32 * Rd2_pro [31:0] $end
$var wire 32 + Rd1_pro [31:0] $end
$var wire 32 , PCout_pro [31:0] $end
$var wire 32 - PCin_pro [31:0] $end
$var wire 5 . MuxReg_pro [4:0] $end
$var wire 32 / MuxMem_pro [31:0] $end
$var wire 32 0 MuxAdderOut_pro [31:0] $end
$var wire 32 1 MuxALU_pro [31:0] $end
$var wire 1 2 MemtoReg_pro $end
$var wire 1 3 MemWrite_pro $end
$var wire 1 4 MemRead_pro $end
$var wire 1 5 Jump_pro $end
$var wire 1 6 Branch_pro $end
$var wire 1 7 AndOut_pro $end
$var wire 32 8 AdderOut_pro [31:0] $end
$var wire 32 9 AdderIn_pro [31:0] $end
$var wire 32 : Add4Out_pro [31:0] $end
$var wire 1 ; ALUSrc_pro $end
$var wire 32 < ALUResult_pro [31:0] $end
$var wire 4 = ALUOperation_pro [3:0] $end
$var wire 2 > ALUOp_pro [1:0] $end
$scope module ALU $end
$var wire 1 $ Zero $end
$var wire 32 ? B [31:0] $end
$var wire 4 @ ALUOperation [3:0] $end
$var wire 32 A A [31:0] $end
$var reg 32 B ALUResult [31:0] $end
$upscope $end
$scope module ALU_Control $end
$var wire 6 C funct [5:0] $end
$var wire 2 D ALUOp [1:0] $end
$var reg 4 E control_out [3:0] $end
$upscope $end
$scope module AND_Gate $end
$var wire 1 7 and_out $end
$var wire 1 $ zero $end
$var wire 1 6 branch $end
$upscope $end
$scope module Adder32 $end
$var wire 32 F sum [31:0] $end
$var wire 32 G B [31:0] $end
$var wire 32 H A [31:0] $end
$upscope $end
$scope module Control $end
$var wire 6 I instruction [31:26] $end
$var reg 2 J ALUOp [1:0] $end
$var reg 1 ; ALUSrc $end
$var reg 1 6 Branch $end
$var reg 1 5 Jump $end
$var reg 1 4 MemRead $end
$var reg 1 3 MemWrite $end
$var reg 1 2 MemtoReg $end
$var reg 1 ( RegDst $end
$var reg 1 ' RegWrite $end
$upscope $end
$scope module DataMemory $end
$var wire 1 4 MemRead $end
$var wire 1 3 MemWrite $end
$var wire 32 K address [31:0] $end
$var wire 1 ! clk $end
$var wire 32 L writeData [31:0] $end
$var wire 32 M readData [31:0] $end
$var integer 32 N i [31:0] $end
$upscope $end
$scope module Inst_Memory $end
$var wire 32 O instruction [31:0] $end
$var wire 32 P addr [31:0] $end
$upscope $end
$scope module MuxALU $end
$var wire 1 ; sel $end
$var wire 32 Q out [31:0] $end
$var wire 32 R B [31:0] $end
$var wire 32 S A [31:0] $end
$upscope $end
$scope module MuxAdder $end
$var wire 32 T B [31:0] $end
$var wire 1 7 sel $end
$var wire 32 U out [31:0] $end
$var wire 32 V A [31:0] $end
$upscope $end
$scope module MuxJump $end
$var wire 32 W A [31:0] $end
$var wire 32 X B [31:0] $end
$var wire 1 5 sel $end
$var wire 32 Y out [31:0] $end
$upscope $end
$scope module MuxMemory $end
$var wire 32 Z A [31:0] $end
$var wire 32 [ B [31:0] $end
$var wire 1 2 sel $end
$var wire 32 \ out [31:0] $end
$upscope $end
$scope module MuxRegFile $end
$var wire 5 ] A [4:0] $end
$var wire 5 ^ B [4:0] $end
$var wire 1 ( sel $end
$var wire 5 _ out [4:0] $end
$upscope $end
$scope module PC $end
$var wire 1 ! clk $end
$var wire 32 ` pc_in [31:0] $end
$var wire 1 " reset $end
$var reg 32 a pc_out [31:0] $end
$upscope $end
$scope module PC_Adder $end
$var wire 32 b in [31:0] $end
$var wire 32 c out [31:0] $end
$upscope $end
$scope module Registers $end
$var wire 32 d ReadData1 [31:0] $end
$var wire 32 e ReadData2 [31:0] $end
$var wire 5 f ReadRegister1 [4:0] $end
$var wire 5 g ReadRegister2 [4:0] $end
$var wire 1 ' RegWrite $end
$var wire 32 h WriteData [31:0] $end
$var wire 5 i WriteRegister [4:0] $end
$var wire 1 ! clk $end
$var integer 32 j i [31:0] $end
$upscope $end
$scope module SLT_Adder $end
$var wire 32 k out [31:0] $end
$var wire 32 l in [31:0] $end
$upscope $end
$scope module SLT_Jump $end
$var wire 26 m in [25:0] $end
$var wire 28 n out [27:0] $end
$upscope $end
$scope module Signal_Ext $end
$var wire 16 o in [15:0] $end
$var wire 32 p out [31:0] $end
$upscope $end
$upscope $end
$upscope $end
$enddefinitions $end
$comment Show the parameter values. $end
$dumpall
$end
#0
$dumpvars
b1010 p
b1010 o
b1000000000000000101000 n
b10000000000000001010 m
b1010 l
b101000 k
b100000 j
b1000 i
b1010 h
b1000 g
b0 f
b0 e
b0 d
b100 c
b0 b
b0 a
b100 `
b1000 _
b0 ^
b1000 ]
b1010 \
b0 [
b1010 Z
b100 Y
b1000000000000000101000 X
b100 W
b100 V
b100 U
b101100 T
b0 S
b1010 R
b1010 Q
b0 P
b100000000010000000000000001010 O
b100000000 N
b0 M
b0 L
b1010 K
b10 J
b1000 I
b100 H
b101000 G
b101100 F
b10 E
b10 D
b1010 C
b1010 B
b0 A
b10 @
b1010 ?
b10 >
b10 =
b1010 <
1;
b100 :
b101000 9
b101100 8
07
06
05
04
03
02
b1010 1
b100 0
b1010 /
b1000 .
b100 -
b0 ,
b0 +
b0 *
b0 )
0(
1'
b1000000000000000101000 &
b1010 %
0$
b100000000010000000000000001010 #
1"
0!
$end
#5
b1010 *
b1010 L
b1010 S
b1010 e
1!
#10
0!
#15
1!
#20
0!
0"
#25
b1100 /
b1100 \
b1100 h
b1100 <
b1100 B
b1100 K
b1100 Z
b1001000000000000110000 X
b1001000000000000110000 &
b1001000000000000110000 n
b110000 9
b110000 G
b110000 k
b1100 1
b1100 ?
b1100 Q
b1001 .
b1001 _
b1001 i
b1000 -
b1000 Y
b1000 `
b10010000000000001100 m
b1100 C
b1100 %
b1100 R
b1100 l
b1100 p
b1100 o
b0 *
b0 L
b0 S
b0 e
b1001 g
b1001 ]
b1000 0
b1000 U
b1000 W
b100000000010010000000000001100 #
b100000000010010000000000001100 O
b111000 8
b111000 F
b111000 T
b1000 :
b1000 H
b1000 V
b1000 c
b100 ,
b100 P
b100 a
b100 b
1!
#30
0!
#35
b10 /
b10 \
b10 h
b100101000010100000010001000 X
b100101000010100000010001000 &
b100101000010100000010001000 n
b110 =
b110 @
b110 E
1(
b10 >
b10 D
b10 J
1'
0;
b10100000010001000 9
b10100000010001000 G
b10100000010001000 k
b1010 1
b1010 ?
b1010 Q
b10 <
b10 B
b10 K
b10 Z
b1010 .
b1010 _
b1010 i
b1100 -
b1100 Y
b1100 `
b1001010000101000000100010 m
b100010 C
b0 I
b101000000100010 %
b101000000100010 R
b101000000100010 l
b101000000100010 p
b101000000100010 o
b1000 g
b1100 +
b1100 A
b1100 d
b1001 f
b1010 ^
b1000 ]
b1100 0
b1100 U
b1100 W
b1001010000101000000100010 #
b1001010000101000000100010 O
b1010 *
b1010 L
b1010 S
b1010 e
b10100000010010100 8
b10100000010010100 F
b10100000010010100 T
b1100 :
b1100 H
b1100 V
b1100 c
b1000 ,
b1000 P
b1000 a
b1000 b
1!
#40
0!
#45
1$
b0 /
b0 \
b0 h
b1010000000000000000000 X
b1010000000000000000000 &
b1010000000000000000000 n
b10 =
b10 @
b10 E
13
x2
1;
b0 >
b0 D
b0 J
0'
0(
b0 9
b0 G
b0 k
b0 1
b0 ?
b0 Q
b0 <
b0 B
b0 K
b0 Z
b1010 .
b1010 _
b1010 i
b10000 -
b10000 Y
b10000 `
b10100000000000000000 m
b0 C
b101011 I
b0 %
b0 R
b0 l
b0 p
b0 o
b10 *
b10 L
b10 S
b10 e
b1010 g
b0 +
b0 A
b0 d
b0 f
b0 ^
b1010 ]
b10000 0
b10000 U
b10000 W
b10101100000010100000000000000000 #
b10101100000010100000000000000000 O
b10000 8
b10000 F
b10000 T
b10000 :
b10000 H
b10000 V
b10000 c
b1100 ,
b1100 P
b1100 a
b1100 b
1!
#50
0!
#55
0$
bx0 /
bx0 \
bx0 h
b100001001000000000000001000 X
b100001001000000000000001000 &
b100001001000000000000001000 n
b110 =
b110 @
b110 E
b1 >
b1 D
b1 J
16
03
x2
0;
b1000 9
b1000 G
b1000 k
b1100 1
b1100 ?
b1100 Q
b11111111111111111111111111111110 <
b11111111111111111111111111111110 B
b11111111111111111111111111111110 K
b11111111111111111111111111111110 Z
b1001 .
b1001 _
b1001 i
b10100 -
b10100 Y
b10100 `
b1000010010000000000000010 m
b10 C
b100 I
b10 %
b10 R
b10 l
b10 p
b10 o
b1100 *
b1100 L
b1100 S
b1100 e
b1001 g
b1010 +
b1010 A
b1010 d
b1000 f
b1001 ]
b10100 0
b10100 U
b10100 W
b10001000010010000000000000010 #
b10001000010010000000000000010 O
b11100 8
b11100 F
b11100 T
b10100 :
b10100 H
b10100 V
b10100 c
b10000 ,
b10000 P
b10000 a
b10000 b
1!
#60
0!
#65
b1011 /
b1011 \
b1011 h
b1011 <
b1011 B
b1011 K
b1011 Z
b100001000000000000000000100 X
b100001000000000000000000100 &
b100001000000000000000000100 n
b10 =
b10 @
b10 E
1'
1;
b10 >
b10 D
b10 J
06
02
b100 9
b100 G
b100 k
b1 1
b1 ?
b1 Q
b1000 .
b1000 _
b1000 i
b11000 -
b11000 Y
b11000 `
b1000010000000000000000001 m
b1 C
b1000 I
b1 %
b1 R
b1 l
b1 p
b1 o
b1010 *
b1010 L
b1010 S
b1010 e
b1000 g
b1000 ]
b11000 0
b11000 U
b11000 W
b100001000010000000000000000001 #
b100001000010000000000000000001 O
b11100 8
b11100 F
b11100 T
b11000 :
b11000 H
b11000 V
b11000 c
b10100 ,
b10100 P
b10100 a
b10100 b
1!
#70
0!
#75
x$
b10000000000000000010000 X
b10000000000000000010000 &
b10000000000000000010000 n
15
x2
x(
bx >
bx D
bx J
0'
x;
b10000 9
b10000 G
b10000 k
b0x00 1
b0x00 ?
b0x00 Q
bx0000 .
bx0000 _
bx0000 i
bx /
bx \
bx h
b10000000000000000010000 -
b10000000000000000010000 Y
b10000000000000000010000 `
b100000000000000000100 m
b100 C
b10 I
b100 %
b100 R
b100 l
b100 p
b100 o
b10000 g
b0 f
b10000 ]
bx <
bx B
bx K
bx Z
b11100 0
b11100 U
b11100 W
b1000000100000000000000000100 #
b1000000100000000000000000100 O
b0 +
b0 A
b0 d
b0 *
b0 L
b0 S
b0 e
b101100 8
b101100 F
b101100 T
b11100 :
b11100 H
b11100 V
b11100 c
b11000 ,
b11000 P
b11000 a
b11000 b
1!
#80
0!
#85
0$
b11111111111111111111111111111111 <
b11111111111111111111111111111111 B
b11111111111111111111111111111111 K
b11111111111111111111111111111111 Z
b10000000000000000010100 -
b10000000000000000010100 Y
b10000000000000000010100 `
07
b100001001000000000000001000 X
b100001001000000000000001000 &
b100001001000000000000001000 n
b110 =
b110 @
b110 E
16
b1 >
b1 D
b1 J
05
x2
0;
0(
b1000 9
b1000 G
b1000 k
b1100 1
b1100 ?
b1100 Q
b1001 .
b1001 _
b1001 i
b1000010010000000000000010 m
b10 C
b100 I
b10 %
b10 R
b10 l
b10 p
b10 o
b1100 *
b1100 L
b1100 S
b1100 e
b1001 g
b1011 +
b1011 A
b1011 d
b1000 f
b1001 ]
b10000000000000000010100 0
b10000000000000000010100 U
b10000000000000000010100 W
b10001000010010000000000000010 #
b10001000010010000000000000010 O
b10000000000000000011100 8
b10000000000000000011100 F
b10000000000000000011100 T
b10000000000000000010100 :
b10000000000000000010100 H
b10000000000000000010100 V
b10000000000000000010100 c
b10000000000000000010000 ,
b10000000000000000010000 P
b10000000000000000010000 a
b10000000000000000010000 b
1!
#90
0!
#95
b1100 /
b1100 \
b1100 h
b1100 <
b1100 B
b1100 K
b1100 Z
b100001000000000000000000100 X
b100001000000000000000000100 &
b100001000000000000000000100 n
b10 =
b10 @
b10 E
1'
1;
b10 >
b10 D
b10 J
06
02
b100 9
b100 G
b100 k
b1 1
b1 ?
b1 Q
b1000 .
b1000 _
b1000 i
b10000000000000000011000 -
b10000000000000000011000 Y
b10000000000000000011000 `
b1000010000000000000000001 m
b1 C
b1000 I
b1 %
b1 R
b1 l
b1 p
b1 o
b1011 *
b1011 L
b1011 S
b1011 e
b1000 g
b1000 ]
b10000000000000000011000 0
b10000000000000000011000 U
b10000000000000000011000 W
b100001000010000000000000000001 #
b100001000010000000000000000001 O
b10000000000000000011100 8
b10000000000000000011100 F
b10000000000000000011100 T
b10000000000000000011000 :
b10000000000000000011000 H
b10000000000000000011000 V
b10000000000000000011000 c
b10000000000000000010100 ,
b10000000000000000010100 P
b10000000000000000010100 a
b10000000000000000010100 b
1!
#100
0!
#105
x$
b10000000000000000010000 X
b10000000000000000010000 &
b10000000000000000010000 n
15
x2
x(
bx >
bx D
bx J
0'
x;
b10000 9
b10000 G
b10000 k
b0x00 1
b0x00 ?
b0x00 Q
bx0000 .
bx0000 _
bx0000 i
bx /
bx \
bx h
b10000000000000000010000 -
b10000000000000000010000 Y
b10000000000000000010000 `
b100000000000000000100 m
b100 C
b10 I
b100 %
b100 R
b100 l
b100 p
b100 o
b10000 g
b0 f
b10000 ]
bx <
bx B
bx K
bx Z
b10000000000000000011100 0
b10000000000000000011100 U
b10000000000000000011100 W
b1000000100000000000000000100 #
b1000000100000000000000000100 O
b0 +
b0 A
b0 d
b0 *
b0 L
b0 S
b0 e
b10000000000000000101100 8
b10000000000000000101100 F
b10000000000000000101100 T
b10000000000000000011100 :
b10000000000000000011100 H
b10000000000000000011100 V
b10000000000000000011100 c
b10000000000000000011000 ,
b10000000000000000011000 P
b10000000000000000011000 a
b10000000000000000011000 b
1!
#110
0!
#115
1$
b0 /
b0 \
b0 h
b0 <
b0 B
b0 K
b0 Z
b10000000000000000011100 -
b10000000000000000011100 Y
b10000000000000000011100 `
17
b100001001000000000000001000 X
b100001001000000000000001000 &
b100001001000000000000001000 n
b110 =
b110 @
b110 E
16
b1 >
b1 D
b1 J
05
x2
0;
0(
b1000 9
b1000 G
b1000 k
b1100 1
b1100 ?
b1100 Q
b1001 .
b1001 _
b1001 i
b1000010010000000000000010 m
b10 C
b100 I
b10 %
b10 R
b10 l
b10 p
b10 o
b1100 *
b1100 L
b1100 S
b1100 e
b1001 g
b1100 +
b1100 A
b1100 d
b1000 f
b1001 ]
b10000000000000000011100 0
b10000000000000000011100 U
b10000000000000000011100 W
b10001000010010000000000000010 #
b10001000010010000000000000010 O
b10000000000000000011100 8
b10000000000000000011100 F
b10000000000000000011100 T
b10000000000000000010100 :
b10000000000000000010100 H
b10000000000000000010100 V
b10000000000000000010100 c
b10000000000000000010000 ,
b10000000000000000010000 P
b10000000000000000010000 a
b10000000000000000010000 b
1!
#120
0!
#125
07
x$
bx /
bx \
bx h
b0xxxxxxxxxxxxxxxxxxxxxxxxxx00 X
bx00 &
bx00 n
b10 =
b10 @
b10 E
b0 >
b0 D
b0 J
06
02
bx00 9
bx00 G
bx00 k
bx 1
bx ?
bx Q
bx <
bx B
bx K
bx Z
bx .
bx _
bx i
b10000000000000000100000 -
b10000000000000000100000 Y
b10000000000000000100000 `
bx m
bx C
bx I
bx %
bx R
bx l
bx p
bx o
bx *
bx L
bx S
bx e
bx g
bx +
bx A
bx d
bx f
bx ^
bx ]
b10000000000000000100000 0
b10000000000000000100000 U
b10000000000000000100000 W
bx #
bx O
bx 8
bx F
bx T
b10000000000000000100000 :
b10000000000000000100000 H
b10000000000000000100000 V
b10000000000000000100000 c
b10000000000000000011100 ,
b10000000000000000011100 P
b10000000000000000011100 a
b10000000000000000011100 b
1!
#130
0!
#135
b10000000000000000100100 -
b10000000000000000100100 Y
b10000000000000000100100 `
b10000000000000000100100 0
b10000000000000000100100 U
b10000000000000000100100 W
b10000000000000000100100 :
b10000000000000000100100 H
b10000000000000000100100 V
b10000000000000000100100 c
b10000000000000000100000 ,
b10000000000000000100000 P
b10000000000000000100000 a
b10000000000000000100000 b
1!
#140
0!
#145
b10000000000000000101000 -
b10000000000000000101000 Y
b10000000000000000101000 `
b10000000000000000101000 0
b10000000000000000101000 U
b10000000000000000101000 W
b10000000000000000101000 :
b10000000000000000101000 H
b10000000000000000101000 V
b10000000000000000101000 c
b10000000000000000100100 ,
b10000000000000000100100 P
b10000000000000000100100 a
b10000000000000000100100 b
1!
#150
0!
