MateusBarreto/jump_address.v
module jump_address (
    input [25:0] instr_target, // Campo target da instrução (26 bits)
    input [31:0] pc_atual,     
    output [31:0] jump_addr    // Endereço de destino do Jump
);
    assign jump_addr = {pc_atual[31:28], instr_target, 2'b00}; // Monta o endereço completo
endmodule

MateusBarreto/somador_pc.v
module somador_pc (
    input [31:0] pc_atual,
    output [31:0] pc_proximo
);
    assign pc_proximo = pc_atual + 32'h00000004;
// é um somador, meio que não precisa de explicação
endmodule

MateusBarreto/memoria_dados.v
module memoria_dados (
    input clk,
    input MemRead, MemWrite,
    input [31:0] endereco, write_data,
    output reg [31:0] read_data
);
    reg [31:0] mem[0:255]; // Memória de 256 palavras de 32 bits

    integer i;
    // Inicializa todas as posições da memória com 0
    initial begin
        for (i = 0; i < 256; i = i + 1)
            mem[i] = 32'b0;
    end

    // Escrita na memória com alinhamento de 4 bytes
    always @(posedge clk) begin
        if (MemWrite)
            mem[endereco[9:2]] <= write_data; // Verifique o alinhamento
    end
    // Leitura com alinhamento de 4 bytes
    always @(*) begin
        if (MemRead)
            read_data = mem[endereco[9:2]];// Leitura 
        else
            read_data = 32'b0;
    end
endmodule

MateusBarreto/ALU.v
module ALU (
    input [31:0] A, B, 
    input [3:0] ALUControl, 
    output reg [31:0] Result, 
    output reg Zero  // Alterado para reg
);
    always @(*) begin
        case(ALUControl)
            4'b0000: Result = A & B;  // AND
            4'b0001: Result = A | B;  // OR
            4'b0010: Result = A + B;  // ADD
            4'b0110: Result = A - B;  // SUB
            4'b0111: Result = (A < B) ? 32'b1 : 32'b0; // SLT
            4'b1100: Result = ~(A | B); // NOR
            default: Result = 32'b0;
        endcase
        Zero = (Result == 32'b0); // Atualiza Zero junto com a ALU
    end
endmodule

MateusBarreto/alu_control.v
module alu_control (
    input [1:0] ALUOp,       // Sinal da Unidade de Controle
    input [5:0] funct,       // Campo 'funct' da instrução do tipo R
    output reg [3:0] ALUControl // Sinal de controle da ALU
);

    always @(*) begin
        case (ALUOp)
            2'b00: ALUControl = 4'b0010; // LW e SW -> ADD
            2'b01: ALUControl = 4'b0110; // BEQ -> SUB
            2'b10: begin // Tipo R -> usa funct
                case (funct)
                    6'b100000: ALUControl = 4'b0010; // ADD
                    6'b100010: ALUControl = 4'b0110; // SUB
                    6'b100100: ALUControl = 4'b0000; // AND
                    6'b100101: ALUControl = 4'b0001; // OR
                    6'b100111: ALUControl = 4'b1100; // NOR
                    6'b000000: ALUControl = 4'b0011; // SLL
                    6'b000010: ALUControl = 4'b0100; // SRL
                    6'b101010: ALUControl = 4'b0111; // SLT
                    default:   ALUControl = 4'b0000; // Padrão (AND)
                endcase
            end
            default: ALUControl = 4'b0000; // AND por padrão
        endcase
    end
endmodule

MateusBarreto/extensor_sinal.v
module extensor_sinal (
    input [15:0] imediato, // Valorde 16 bits
    output [31:0] imediato_ext // Valor estendido para 32 bits
);
    assign imediato_ext = {{16{imediato[15]}}, imediato}; // Extensão de sinal
endmodule

MateusBarreto/banco_registradores.v
module banco_registradores (
    input clk,
    input RegWrite, // Sinal de escrita
    input [4:0] read_reg1, read_reg2, write_reg, // Endereços dos registradores
    input [31:0] write_data, // Dado para escrita
    output reg [31:0] read_data1, read_data2 // Saídas 
);
    //registradores
    reg [31:0] registradores [0:31]; 

    integer i;
    initial begin
        for (i = 0; i < 32; i = i + 1)
            registradores[i] = 0; // Inicializa todos os registradores com 0 (Evita 'X')
    end

    // Escrita no registrador (somente na borda de subida do clock)
    always @(posedge clk) begin
        if (RegWrite && write_reg != 0) // Evita escrita no registrador $zero
            registradores[write_reg] <= write_data;
    end

    // Leitura dos registradores
    always @(*) begin
        read_data1 = registradores[read_reg1];
        read_data2 = registradores[read_reg2];
    end
endmodule

MateusBarreto/unidade_controle.v
module unidade_controle (
    input [5:0] opcode,    // código de operação (opcode)
    output reg RegDst,     // controle para selecionar o destino do registrador
    output reg ALUSrc,     // controle para escolher entre registrador ou imediato para ALU
    output reg MemtoReg,   // controle para selecionar entre ALU e memória para registrador de destino
    output reg RegWrite,   // habilitação para escrita em registrador
    output reg MemRead,    // controle para ler da memória
    output reg MemWrite,   // controle para escrever na memória
    output reg Branch,     // controle para operações de salto condicional
    output reg Jump,       // controle para operações de salto incondicional
    output reg [1:0] ALUOp // controle para selecionar a operação da ALU
);
    always @(*) begin
        case(opcode) // Dependendo do valor do opcode, define-se os sinais de controle
            6'b000000: begin // R-R
                RegDst   = 1;    
                ALUSrc   = 0;    
                MemtoReg = 0;    
                RegWrite = 1;    // A escrita no registrador é habilitada
                MemRead  = 0;    
                MemWrite = 0;    
                Branch   = 0;    
                Jump     = 0;    
                ALUOp    = 2'b10; // A ALU realiza uma operação aritmética (add, sub, etc.)
            end
            6'b100011: begin // LW (Load Word) 
                RegDst   = 0;    
                ALUSrc   = 1;    // Usa o valor imediato (offset) como segundo operando para a ALU
                MemtoReg = 1;    // O valor de destino do registrador vem da memória
                RegWrite = 1;    // A escrita no registrador é habilitada
                MemRead  = 1;    // Realiza a leitura da memória
                MemWrite = 0;     
                Branch   = 0;    
                Jump     = 0;    
                ALUOp    = 2'b00; // A ALU realiza uma operação de soma para calcular o endereço
            end
            6'b101011: begin // SW (Store Word) 
                RegDst   = 0;    
                ALUSrc   = 1;    // Usa o valor imediato (offset) como segundo operando para a ALU
                MemtoReg = 0;    
                RegWrite = 0;    
                MemRead  = 0;    
                MemWrite = 1;    // Realiza a escrita na memória
                Branch   = 0;    
                Jump     = 0;    
                ALUOp    = 2'b00; // Memsa coisa da de cima
            end
            6'b000100: begin // BEQ (Branch if Equal) 
                RegDst   = 0;    
                ALUSrc   = 0;    
                MemtoReg = 0;    
                RegWrite = 0;    
                MemRead  = 0;    
                MemWrite = 0;    
                Branch   = 1;    // Realiza o salto se for true
                Jump     = 0;    
                ALUOp    = 2'b01; // A ULA realiza uma operação de subtração para verificar igualdade
            end
            6'b000010: begin // JUMP (J) 
                RegDst   = 0;    
                ALUSrc   = 0;    
                MemtoReg = 0;    
                RegWrite = 0;    
                MemRead  = 0;    
                MemWrite = 0;    
                Branch   = 0;    
                Jump     = 1;    // Realiza o JUMP
                ALUOp    = 2'b00; // Nenhuma operação de ALU é realizada
            end
            6'b001000: begin // ADDI (Add Immediate) 
                RegDst   = 0;    
                ALUSrc   = 1;    // Usa o valor imediato  como segundo operando
                MemtoReg = 0;    
                RegWrite = 1;    // A escrita no registrador é habilitadaa
                MemRead  = 0;    
                MemWrite = 0;    
                Branch   = 0;   
                Jump     = 0;    
                ALUOp    = 2'b00; // Mesmo da de cima
            end
            default: begin // Caso default para opcode não reconhecido
                RegDst   = 0;
                ALUSrc   = 0;
                MemtoReg = 0;
                RegWrite = 0;
                MemRead  = 0;
                MemWrite = 0;
                Branch   = 0;
                Jump     = 0;
                ALUOp    = 2'b00; 
            end
        endcase
    end
endmodule

MateusBarreto/memoria_instrucoes.v
module memoria_instrucoes (
    input [31:0] endereco,   // Endereço da instrução 
    output reg [31:0] instrucao // Instrução lida
);
    // Memória de instruções: 256 palavras de 32 bits
    reg [31:0] mem [0:255];

    // Inicializa a memória com um programa
    initial begin
        
        instrucao = 32'b0;
        $readmemb("instrucoes.mem", mem, 0, 9);
 
    end

    // Leitura da memória (com proteção contra endereços inválidos, fiz isso pq queria 
    //	limitar a qtd de instruções, tive alguns problemas)
    always @(*) begin
        if (endereco[9:2] <= 9)  // Verifica se está dentro dos 10 primeiros endereços
            instrucao = mem[endereco[9:2]];
        else
            instrucao = 32'b0;  // Retorna uma instrução NOP caso o endereço não seja valido
    end
endmodule

MateusBarreto/program_counter.v
module program_counter (
    input clk, reset, Jump, Branch, Zero,
    input [31:0] pc_next, jump_addr, branch_target,
    output reg [31:0] pc
);
    always @(posedge clk or posedge reset) begin
        if (reset)
            pc <= 32'h00000000;      // Inicializa o PC em 0
        else if (Jump)
            pc <= jump_addr;         // JUMP
        else if (Branch && Zero)
            pc <= branch_target;     // Salta para  o branch_target 
        else
            pc <= pc_next & 32'hFFFFFFFC; // PC normal, mantendo alinhamento de 4 bytes
    end
endmodule

MateusBarreto/mips_ciclo_unico.v
`include "program_counter.v"
`include "memoria_instrucoes.v"
`include "unidade_controle.v"
`include "banco_registradores.v"
`include "extensor_sinal.v"
`include "alu_control.v"
`include "ALU.v"
`include "memoria_dados.v"
`include "somador_pc.v"
`include "jump_address.v"

module mips_ciclo_unico (
    input clk, reset
);
    wire [31:0] pc_atual, pc_proximo, instrucao, read_data1, read_data2;
    wire [31:0] imediato_ext, alu_resultado, mem_dados, write_data, jump_addr;
    wire [31:0] branch_target;  // Novo sinal para branch target
    wire [4:0] write_reg;
    wire [3:0] ALUControl;
    wire [1:0] ALUOp;
    wire [31:0] alu_operand2;
    wire Zero, RegDst, ALUSrc, MemtoReg, RegWrite, MemRead, MemWrite, Branch, Jump;
    
    // calcula o branch target: PC+4 + (imediato_ext << 2)
    assign branch_target = pc_proximo + (imediato_ext << 2);

    // instancia o program ccounter com suporte a Jump e Branch
    program_counter PC(
        clk,       // clk
        reset,     // reset
        Jump,      // sinal de Jump
        Branch,    // sinal de Branch
        Zero,      // sinal Zero (saída da ALU)
        pc_proximo,// pc + 4
        jump_addr, // endereço para Jump
        branch_target, // endereço para Branch
        pc_atual   // pc atual (saída)
    );
    
    // Memória de Instruções
    memoria_instrucoes MEM_INST(
        pc_atual, 
        instrucao
    );
    
    // Unidade de Controle
    unidade_controle CTRL(
        instrucao[31:26], 
        RegDst, ALUSrc, MemtoReg, RegWrite, MemRead, MemWrite, Branch, Jump, ALUOp
    );
    
    // Banco de Registradores
    assign write_reg = (RegDst) ? instrucao[15:11] : instrucao[20:16];
    banco_registradores REGISTROS(
        clk, 
        RegWrite, 
        instrucao[25:21], 
        instrucao[20:16], 
        write_reg, 
        write_data, 
        read_data1, 
        read_data2
    );
    
    // Extensor de Sinal
    extensor_sinal EXT(
        instrucao[15:0], 
        imediato_ext
    );
    
    // Multiplexador para a ALU
    assign alu_operand2 = (ALUSrc) ? imediato_ext : read_data2;
 

    // ALU Control
    alu_control ALU_CTRL(
        ALUOp, 
        instrucao[5:0], 
        ALUControl
    );
    
    // ALU
    ALU ALU_MOD(
        read_data1, 
        alu_operand2, 
        ALUControl, 
        alu_resultado, 
        Zero
    );
    
    // Memória de Dados
    memoria_dados MEM_DADOS(
        clk, 
        MemRead, 
        MemWrite, 
        alu_resultado, 
        read_data2, 
        mem_dados
    );
    
    // Multiplexador para escrita no banco de registradores
    assign write_data = (MemtoReg) ? mem_dados : alu_resultado;
    

    // Somador de PC (PC + 4)
    somador_pc SOMADOR(
        pc_atual, 
        pc_proximo
    );

    // calculo do endereço do Jump
    jump_address JUMP_MOD(
        instrucao[25:0], 
        pc_atual, 
        jump_addr
    );
    
endmodule

MateusBarreto/TB_MIPS.v
`timescale 1ns/1ps

module testbench_mips;
    reg clk, reset;

    // instancia o processador MIPS de ciclo único
    mips_ciclo_unico UUT (
        .clk(clk),
        .reset(reset)
    );

    // Geração do Clock 
    always #10 clk = ~clk;
    initial begin
        $dumpfile("mips_tb.vcd");  // Arquivo de saída pro GTK
        $dumpvars(0, testbench_mips);

        // inicializa sinais
        clk = 0;
        reset = 1;

        #20 reset = 0; // 

        // Monitora a execução a cada ciclo de clock
        repeat (20) begin  // Executa por 20 ciclos
            #20;
            $display("PC = %h, Instrucao = %b", UUT.pc_atual, UUT.MEM_INST.instrucao);
        end

        // Exibe os valores dos registradores (todos os 32)
        $display("\n=== REGISTRADORES ===");
        for (integer i = 0; i < 32; i = i + 1) begin
            $display("R%0d: %d", i, UUT.REGISTROS.registradores[i]);
        end

        // exibe os valores da memoria para verificar operações de Load e Store (todas as 256 posições)
        $display("\n=== MEMORIA DE DADOS ===");
        for (integer i = 0; i < 256; i = i + 1) begin
            $display("Mem[%0d]: %d", i, UUT.MEM_DADOS.mem[i]);
        end

        // Finaliza a simulaçao
        #100 $finish;
    end
endmodule

MateusBarreto/mips_tb.vcd
$date
	Sun Feb 16 23:20:09 2025
$end
$version
	Icarus Verilog
$end
$timescale
	1ps
$end
$scope module testbench_mips $end
$var reg 1 ! clk $end
$var reg 1 " reset $end
$scope module UUT $end
$var wire 1 ! clk $end
$var wire 1 " reset $end
$var wire 5 # write_reg [4:0] $end
$var wire 32 $ write_data [31:0] $end
$var wire 32 % read_data2 [31:0] $end
$var wire 32 & read_data1 [31:0] $end
$var wire 32 ' pc_proximo [31:0] $end
$var wire 32 ( pc_atual [31:0] $end
$var wire 32 ) mem_dados [31:0] $end
$var wire 32 * jump_addr [31:0] $end
$var wire 32 + instrucao [31:0] $end
$var wire 32 , imediato_ext [31:0] $end
$var wire 32 - branch_target [31:0] $end
$var wire 32 . alu_resultado [31:0] $end
$var wire 32 / alu_operand2 [31:0] $end
$var wire 1 0 Zero $end
$var wire 1 1 RegWrite $end
$var wire 1 2 RegDst $end
$var wire 1 3 MemtoReg $end
$var wire 1 4 MemWrite $end
$var wire 1 5 MemRead $end
$var wire 1 6 Jump $end
$var wire 1 7 Branch $end
$var wire 1 8 ALUSrc $end
$var wire 2 9 ALUOp [1:0] $end
$var wire 4 : ALUControl [3:0] $end
$scope module ALU_CTRL $end
$var wire 6 ; funct [5:0] $end
$var wire 2 < ALUOp [1:0] $end
$var reg 4 = ALUControl [3:0] $end
$upscope $end
$scope module ALU_MOD $end
$var wire 4 > ALUControl [3:0] $end
$var wire 32 ? B [31:0] $end
$var wire 32 @ A [31:0] $end
$var reg 32 A Result [31:0] $end
$var reg 1 0 Zero $end
$upscope $end
$scope module CTRL $end
$var wire 6 B opcode [5:0] $end
$var reg 2 C ALUOp [1:0] $end
$var reg 1 8 ALUSrc $end
$var reg 1 7 Branch $end
$var reg 1 6 Jump $end
$var reg 1 5 MemRead $end
$var reg 1 4 MemWrite $end
$var reg 1 3 MemtoReg $end
$var reg 1 2 RegDst $end
$var reg 1 1 RegWrite $end
$upscope $end
$scope module EXT $end
$var wire 16 D imediato [15:0] $end
$var wire 32 E imediato_ext [31:0] $end
$upscope $end
$scope module JUMP_MOD $end
$var wire 26 F instr_target [25:0] $end
$var wire 32 G pc_atual [31:0] $end
$var wire 32 H jump_addr [31:0] $end
$upscope $end
$scope module MEM_DADOS $end
$var wire 1 5 MemRead $end
$var wire 1 4 MemWrite $end
$var wire 1 ! clk $end
$var wire 32 I endereco [31:0] $end
$var wire 32 J write_data [31:0] $end
$var reg 32 K read_data [31:0] $end
$var integer 32 L i [31:0] $end
$upscope $end
$scope module MEM_INST $end
$var wire 32 M endereco [31:0] $end
$var reg 32 N instrucao [31:0] $end
$upscope $end
$scope module PC $end
$var wire 1 7 Branch $end
$var wire 1 6 Jump $end
$var wire 1 0 Zero $end
$var wire 32 O branch_target [31:0] $end
$var wire 1 ! clk $end
$var wire 32 P jump_addr [31:0] $end
$var wire 1 " reset $end
$var wire 32 Q pc_next [31:0] $end
$var reg 32 R pc [31:0] $end
$upscope $end
$scope module REGISTROS $end
$var wire 1 1 RegWrite $end
$var wire 1 ! clk $end
$var wire 5 S read_reg1 [4:0] $end
$var wire 5 T read_reg2 [4:0] $end
$var wire 32 U write_data [31:0] $end
$var wire 5 V write_reg [4:0] $end
$var reg 32 W read_data1 [31:0] $end
$var reg 32 X read_data2 [31:0] $end
$var integer 32 Y i [31:0] $end
$upscope $end
$scope module SOMADOR $end
$var wire 32 Z pc_atual [31:0] $end
$var wire 32 [ pc_proximo [31:0] $end
$upscope $end
$upscope $end
$scope begin $ivl_for_loop0 $end
$var integer 32 \ i [31:0] $end
$upscope $end
$scope begin $ivl_for_loop1 $end
$var integer 32 ] i [31:0] $end
$upscope $end
$upscope $end
$enddefinitions $end
$comment Show the parameter values. $end
$dumpall
$end
#0
$dumpvars
bx ]
bx \
b100 [
b0 Z
b100000 Y
b0 X
b0 W
b1 V
b1000 U
b1 T
b0 S
b0 R
b100 Q
b1000000000000100000 P
b100100 O
b100000000000010000000000001000 N
b0 M
b100000000 L
b0 K
b0 J
b1000 I
b1000000000000100000 H
b0 G
b10000000000001000 F
b1000 E
b1000 D
b0 C
b1000 B
b1000 A
b0 @
b1000 ?
b10 >
b10 =
b0 <
b1000 ;
b10 :
b0 9
18
07
06
05
04
03
02
11
00
b1000 /
b1000 .
b100100 -
b1000 ,
b100000000000010000000000001000 +
b1000000000000100000 *
b0 )
b0 (
b100 '
b0 &
b0 %
b1000 $
b1 #
1"
0!
$end
#10000
b1000 %
b1000 J
b1000 X
1!
#20000
0!
0"
#30000
b10000 $
b10000 U
b10000 .
b10000 A
b10000 I
b10000 /
b10000 ?
b0 %
b0 J
b0 X
b10 #
b10 V
b10000000000001000000 *
b10000000000001000000 H
b10000000000001000000 P
b100000000000010000 F
b10000 ;
b10000 ,
b10000 E
b10000 D
b10 T
b100000000000100000000000010000 +
b100000000000100000000000010000 N
b1001000 -
b1001000 O
b1000 '
b1000 Q
b1000 [
b100 (
b100 G
b100 M
b100 R
b100 Z
1!
#40000
0!
#50000
b11000 $
b11000 U
b11000 .
b11000 A
b11000 I
b11 #
b11 V
b1000 &
b1000 @
b1000 W
b10 9
b10 <
b10 C
08
12
b100010000110000010000000 *
b100010000110000010000000 H
b100010000110000010000000 P
b1000100001100000100000 F
b100000 ;
b1100000100000 ,
b1100000100000 E
b1100000100000 D
b1 S
b0 B
b10000 %
b10000 J
b10000 X
b1000100001100000100000 +
b1000100001100000100000 N
b110000010001100 -
b110000010001100 O
b1100 '
b1100 Q
b1100 [
b1000 (
b1000 G
b1000 M
b1000 R
b1000 Z
1!
#60000
0!
#70000
b1100 .
b1100 A
b1100 I
b0 $
b0 U
b100 /
b100 ?
b0 %
b0 J
b0 X
b100 #
b100 V
b0 9
b0 <
b0 C
15
13
18
02
b100100000000000000010000 *
b100100000000000000010000 H
b100100000000000000010000 P
b1001000000000000000100 F
b100 ;
b100 ,
b100 E
b100 D
b100 T
b100011 B
b10001100001001000000000000000100 +
b10001100001001000000000000000100 N
b100000 -
b100000 O
b10000 '
b10000 Q
b10000 [
b1100 (
b1100 G
b1100 M
b1100 R
b1100 Z
1!
#80000
0!
#90000
b10000 .
b10000 A
b10000 I
b10000 $
b10000 U
b1000 /
b1000 ?
b11000 %
b11000 J
b11000 X
b11 #
b11 V
14
05
01
03
b100011000000000000100000 *
b100011000000000000100000 H
b100011000000000000100000 P
b1000110000000000001000 F
b1000 ;
b1000 ,
b1000 E
b1000 D
b11 T
b101011 B
b10101100001000110000000000001000 +
b10101100001000110000000000001000 N
b110100 -
b110100 O
b10100 '
b10100 Q
b10100 [
b10000 (
b10000 G
b10000 M
b10000 R
b10000 Z
1!
#100000
0!
#110000
b11000 $
b11000 U
b11000 .
b11000 A
b11000 I
b110 :
b110 =
b110 >
b0 /
b0 ?
b0 %
b0 J
b0 X
b11000 &
b11000 @
b11000 W
b100 #
b100 V
b1 9
b1 <
b1 C
17
04
08
b1100100000000000000000100 *
b1100100000000000000000100 H
b1100100000000000000000100 P
b11001000000000000000001 F
b1 ;
b1 ,
b1 E
b1 D
b100 T
b11 S
b100 B
b10000011001000000000000000001 +
b10000011001000000000000000001 N
b11100 -
b11100 O
b11000 '
b11000 Q
b11000 [
b10100 (
b10100 G
b10100 M
b10100 R
b10100 Z
1!
#120000
0!
#130000
b1100011 $
b1100011 U
b1100011 .
b1100011 A
b1100011 I
b1100011 /
b1100011 ?
b10 :
b10 =
b10 >
b0 &
b0 @
b0 W
b101 #
b101 V
b0 9
b0 <
b0 C
07
11
18
b101000000000110001100 *
b101000000000110001100 H
b101000000000110001100 P
b1010000000001100011 F
b100011 ;
b1100011 ,
b1100011 E
b1100011 D
b101 T
b0 S
b1000 B
b100000000001010000000001100011 +
b100000000001010000000001100011 N
b110101000 -
b110101000 O
b11100 '
b11100 Q
b11100 [
b11000 (
b11000 G
b11000 M
b11000 R
b11000 Z
1!
#140000
0!
#150000
b0 $
b0 U
10
b0 .
b0 A
b0 I
b0 /
b0 ?
b0 #
b0 V
16
01
08
b111000 *
b111000 H
b111000 P
b1110 F
b1110 ;
b1110 ,
b1110 E
b1110 D
b0 T
b10 B
b0 %
b0 J
b0 X
b1000000000000000000000001110 +
b1000000000000000000000001110 N
b1011000 -
b1011000 O
b100000 '
b100000 Q
b100000 [
b11100 (
b11100 G
b11100 M
b11100 R
b11100 Z
1!
#160000
0!
#170000
b11 :
b11 =
b11 >
b10 9
b10 <
b10 C
06
11
12
b0 *
b0 H
b0 P
b0 F
b0 ;
b0 ,
b0 E
b0 D
b0 B
b0 +
b0 N
b111100 -
b111100 O
b111100 '
b111100 Q
b111100 [
b111000 (
b111000 G
b111000 M
b111000 R
b111000 Z
1!
#180000
0!
#190000
b1000000 -
b1000000 O
b1000000 '
b1000000 Q
b1000000 [
b111100 (
b111100 G
b111100 M
b111100 R
b111100 Z
1!
#200000
0!
#210000
b1000100 -
b1000100 O
b1000100 '
b1000100 Q
b1000100 [
b1000000 (
b1000000 G
b1000000 M
b1000000 R
b1000000 Z
1!
#220000
0!
#230000
b1001000 -
b1001000 O
b1001000 '
b1001000 Q
b1001000 [
b1000100 (
b1000100 G
b1000100 M
b1000100 R
b1000100 Z
1!
#240000
0!
#250000
b1001100 -
b1001100 O
b1001100 '
b1001100 Q
b1001100 [
b1001000 (
b1001000 G
b1001000 M
b1001000 R
b1001000 Z
1!
#260000
0!
#270000
b1010000 -
b1010000 O
b1010000 '
b1010000 Q
b1010000 [
b1001100 (
b1001100 G
b1001100 M
b1001100 R
b1001100 Z
1!
#280000
0!
#290000
b1010100 -
b1010100 O
b1010100 '
b1010100 Q
b1010100 [
b1010000 (
b1010000 G
b1010000 M
b1010000 R
b1010000 Z
1!
#300000
0!
#310000
b1011000 -
b1011000 O
b1011000 '
b1011000 Q
b1011000 [
b1010100 (
b1010100 G
b1010100 M
b1010100 R
b1010100 Z
1!
#320000
0!
#330000
b1011100 -
b1011100 O
b1011100 '
b1011100 Q
b1011100 [
b1011000 (
b1011000 G
b1011000 M
b1011000 R
b1011000 Z
1!
#340000
0!
#350000
b1100000 -
b1100000 O
b1100000 '
b1100000 Q
b1100000 [
b1011100 (
b1011100 G
b1011100 M
b1011100 R
b1011100 Z
1!
#360000
0!
#370000
b1100100 -
b1100100 O
b1100100 '
b1100100 Q
b1100100 [
b1100000 (
b1100000 G
b1100000 M
b1100000 R
b1100000 Z
1!
#380000
0!
#390000
b1101000 -
b1101000 O
b1101000 '
b1101000 Q
b1101000 [
b1100100 (
b1100100 G
b1100100 M
b1100100 R
b1100100 Z
1!
#400000
0!
#410000
b1101100 -
b1101100 O
b1101100 '
b1101100 Q
b1101100 [
b1101000 (
b1101000 G
b1101000 M
b1101000 R
b1101000 Z
1!
#420000
0!
b100000000 ]
b100000 \
#430000
b1110000 -
b1110000 O
b1110000 '
b1110000 Q
b1110000 [
b1101100 (
b1101100 G
b1101100 M
b1101100 R
b1101100 Z
1!
#440000
0!
#450000
b1110100 -
b1110100 O
b1110100 '
b1110100 Q
b1110100 [
b1110000 (
b1110000 G
b1110000 M
b1110000 R
b1110000 Z
1!
#460000
0!
#470000
b1111000 -
b1111000 O
b1111000 '
b1111000 Q
b1111000 [
b1110100 (
b1110100 G
b1110100 M
b1110100 R
b1110100 Z
1!
#480000
0!
#490000
b1111100 -
b1111100 O
b1111100 '
b1111100 Q
b1111100 [
b1111000 (
b1111000 G
b1111000 M
b1111000 R
b1111000 Z
1!
#500000
0!
#510000
b10000000 -
b10000000 O
b10000000 '
b10000000 Q
b10000000 [
b1111100 (
b1111100 G
b1111100 M
b1111100 R
b1111100 Z
1!
