JosephAntony/ControleULA/controleULA.v
module controleULA(opALU, funct, ALUcontrol);
    input [1:0] opALU;
    input [5:0] funct;
    output reg [3:0] ALUcontrol;


    always @(*)begin
        if (opALU == 2'b00) begin
            ALUcontrol = 4'b0010;
        end
        else if (opALU == 2'b01) begin
            ALUcontrol = 4'b0110;
        end
        else if (opALU == 2'b10) begin
            if (funct == 6'b100000) begin
                ALUcontrol = 4'b0010;
            end
            else if (funct == 6'b100010) begin
                ALUcontrol = 4'b0110;
            end
            else if (funct == 6'b100100) begin
                ALUcontrol = 4'b0000;
            end
            else if (funct == 6'b100101) begin
                ALUcontrol = 4'b0001;
            end
            else if (funct == 6'b101010) begin
                ALUcontrol = 4'b0111;
            end
            else begin
                ALUcontrol = 4'b0000;
            end
        end
        else begin
            ALUcontrol = 4'b0000;
        end
    end
endmodule

JosephAntony/ControleULA/testbenchControleULA.v
`timescale 1ns/1ps

    module testbenchControleULA;
        reg [1:0] opALU;
        reg [5:0] funct;
        wire [3:0] ALUcontrol;

        controleULA uut(
            .opALU(opALU),
            .funct(funct),
            .ALUcontrol(ALUcontrol)
        );

        initial begin
        $dumpfile("testbenchControleULA.vcd");
        $dumpvars(0, testbenchControleULA, opALU, funct, ALUcontrol);

        $monitor("opALU: %b | funct: %b | ALUControl: %b", opALU, funct, ALUcontrol);


        opALU = 2'b00; funct = 6'b000000; #10;  // soma LW ou SW
        opALU = 2'b01; funct = 6'b000000; #10;  // sub  beq
        opALU = 2'b10; funct = 6'b100000; #10;  // soma do tipo R
        opALU = 2'b10; funct = 6'b100010; #10;  // sub do tipo R
        opALU = 2'b10; funct = 6'b100100; #10;  // and do tipo R
        opALU = 2'b10; funct = 6'b100101; #10;  // or do tipo R
        opALU = 2'b10; funct = 6'b101010; #10;  // slt do tipo R
        opALU = 2'b10; funct = 6'b000000; #10;  // instrucao invalida


        #30;
        $finish;
        end
    endmodule

JosephAntony/ControleULA/testbenchControleULA.vcd
$date
	Fri Feb 07 10:11:03 2025
$end
$version
	Icarus Verilog
$end
$timescale
	1ps
$end
$scope module testbenchControleULA $end
$var wire 4 ! ALUcontrol [3:0] $end
$var reg 6 " funct [5:0] $end
$var reg 2 # opALU [1:0] $end
$scope module uut $end
$var wire 6 $ funct [5:0] $end
$var wire 2 % opALU [1:0] $end
$var reg 4 & ALUcontrol [3:0] $end
$upscope $end
$upscope $end
$enddefinitions $end
$comment Show the parameter values. $end
$dumpall
$end
#0
$dumpvars
b10 &
b0 %
b0 $
b0 #
b0 "
b10 !
$end
#10000
b110 !
b110 &
b1 #
b1 %
#20000
b10 !
b10 &
b100000 "
b100000 $
b10 #
b10 %
#30000
b110 !
b110 &
b100010 "
b100010 $
#40000
b0 !
b0 &
b100100 "
b100100 $
#50000
b1 !
b1 &
b100101 "
b100101 $
#60000
b111 !
b111 &
b101010 "
b101010 $
#70000
b0 !
b0 &
b0 "
b0 $
