ThiagoMarcelMessias/MemoriaDeInstrucoes.v
module MemoriaDeInstrucoes(
    input wire [31:0] addr,        // Endereço da instrução
    output wire [31:0] instrucao   // Instrução lida
);
    // Memória de instruções (1.024 palavras de 32 bits)
    reg [31:0] memoria [0:1023];   // 1.024 palavras de 32 bits

    // Inicialização da memória com o arquivo binário
    initial begin
        $readmemh("codigo.mem", memoria);  // Lê até 1.024 palavras de 32 bits do arquivo hex
    end

    // Leitura combinacional: usa os bits 11 a 2 para acessar a memória
    assign instrucao = memoria[addr[11:2]];  // Acesso à memória com os bits 11 a 2 do endereço
endmodule

ThiagoMarcelMessias/DataMemory.v
module DataMemory(
    input wire clk,                // Clock
    input wire MemRead,            // Sinal de leitura
    input wire MemWrite,           // Sinal de escrita
    input wire [31:0] address,     // Endereço de memória
    input wire [31:0] writeData,   // Dados a serem escritos
    output reg [31:0] readData     // Dados lidos
);

    // Memória de dados (256 palavras de 32 bits)
    reg [31:0] memory [255:0];

    // Inicializa a memória para simulação (opcional)
    integer i;
    initial begin
        for (i = 0; i < 256; i = i + 1) begin
            memory[i] = 32'b0; 
        end
    end

    // Leitura condicional: a leitura acontece apenas se MemRead for 1
    always @(*) begin
        if (MemRead) begin
            readData = memory[address[9:2]]; 
        end else begin
            readData = 32'b0; 
        end
    end

    // Escrita condicional: a escrita acontece apenas se MemWrite for 1
    always @(posedge clk) begin
        if (MemWrite) begin
            memory[address[9:2]] <= writeData; 
        end
    end

endmodule

ThiagoMarcelMessias/ALU.v
module ALU(
    input [31:0] A,           // Operando A
    input [31:0] B,           // Operando B
    input [3:0] ALU_Control,  // Controle da ALU
    output reg [31:0] Result, // Resultado da operação
    output reg Zero           // Sinal Zero (para BEQ)
);

    always @(*) begin
        
        case (ALU_Control)
            4'b0010: Result = A + B;    // Operação de soma
            4'b0110: Result = A - B;    // Operação de subtração
            4'b0000: Result = A & B;    // Operação AND
            4'b0001: Result = A | B;    // Operação OR
            4'b0111: Result = (A < B) ? 1 : 0;  // SLT
            default: Result = 32'b0;    // Default, pode ser uma operação inválida
        endcase
        
        // Sinal Zero
        Zero = (Result == 32'b0) ? 1 : 0; // Verifica se o resultado é zero
    end
endmodule

ThiagoMarcelMessias/ALUControl.v
module ALUControl(
    input [1:0] ALUOp,       // Entrada de controle da ALU 
    input [5:0] Func,        // Campo funct da instrução 
    output reg [3:0] ALU_Control // Sinal de controle da ALU 
);

    wire [7:0] ALUControlIn;
    assign ALUControlIn = {ALUOp, Func};

    always @(*) begin
        case (ALUControlIn)
            8'b00xxxxxx: ALU_Control = 4'b0010; // LW e SW (soma)
            8'b01xxxxxx: ALU_Control = 4'b0110; // BEQ (subtração)
            8'b10100000: ALU_Control = 4'b0010; // ADD 
            8'b10100010: ALU_Control = 4'b0110; // SUB
            8'b10100100: ALU_Control = 4'b0000; // AND
            8'b10100101: ALU_Control = 4'b0001; // OR
            8'b10101010: ALU_Control = 4'b0111; // SLT (set less than)
            default: ALU_Control = 4'b0010;     // Default (soma)
        endcase
    end

endmodule



module JR_Control(
    input [1:0] alu_op,      // Entrada de controle da ALU 
    input [5:0] funct,       // Campo funct da instrução 
    output reg JRControl     // Sinal de controle para instrução JR
);

    wire [7:0] JRControlIn;
    assign JRControlIn = {alu_op, funct};

    always @(*) begin
        JRControl = (JRControlIn == 8'b11001000) ? 1'b1 : 1'b0; // JR 
    end

endmodule

ThiagoMarcelMessias/Registradores.v
module Registradores(
    input wire clk,                // Clock
    input wire [4:0] ReadRegister1, // Endereço de leitura 1
    input wire [4:0] ReadRegister2, // Endereço de leitura 2
    input wire [4:0] WriteRegister, // Endereço de escrita
    input wire [31:0] WriteData,    // Dados a serem escritos
    input wire RegWrite,            // Habilitação de escrita
    output wire [31:0] ReadData1,   // Dados lidos do registrador 1
    output wire [31:0] ReadData2    // Dados lidos do registrador 2
);

    // Banco de 32 registradores de 32 bits
    reg [31:0] registers [31:0];

    // Inicializa os registradores
    integer i;
    initial begin
        for (i = 0; i < 32; i = i + 1) begin
            registers[i] = 32'b0;  // Inicializa todos com zero
        end
    end

    // Leitura combinacional
    assign ReadData1 = registers[ReadRegister1];
    assign ReadData2 = registers[ReadRegister2];

    // Escrita no registrador (sincronizada no clock)
    always @(posedge clk) begin
        if (RegWrite && WriteRegister != 5'b0) begin
            registers[WriteRegister] <= WriteData;  // Escreve no registrador
        end
    end

endmodule

ThiagoMarcelMessias/control.v
module control( 
    input [5:0] opcode,  
    input reset,         
    output reg [1:0] reg_dst,  
    output reg [1:0] mem_to_reg,  
    output reg [1:0] alu_op,  
    output reg jump,  
    output reg branch,  
    output reg mem_read,  
    output reg mem_write,  
    output reg alu_src,  
    output reg reg_write,  
    output reg sign_or_zero  
);

    always @(*) begin  
        if (reset == 1'b1) begin  
            // Sinais de controle padrão no reset
            reg_dst = 2'b00;  
            mem_to_reg = 2'b00;  
            alu_op = 2'b00;  
            jump = 1'b0;  
            branch = 1'b0;  
            mem_read = 1'b0;  
            mem_write = 1'b0;  
            alu_src = 1'b0;  
            reg_write = 1'b0;  
            sign_or_zero = 1'b1;   
        end  
        else begin  
            case(opcode)   
                6'b000000: begin  // R-type (Ex: add, sub, and, or, etc)
                    reg_dst = 2'b01;  
                    mem_to_reg = 2'b00;  
                    alu_op = 2'b10;  
                    jump = 1'b0;  
                    branch = 1'b0;  
                    mem_read = 1'b0;  
                    mem_write = 1'b0;  
                    alu_src = 1'b0;  
                    reg_write = 1'b1;  
                    sign_or_zero = 1'b1;  
                end  
                6'b100011: begin  // lw (Load Word)
                    reg_dst = 2'b00;  
                    mem_to_reg = 2'b01;  
                    alu_op = 2'b00;  
                    jump = 1'b0;  
                    branch = 1'b0;  
                    mem_read = 1'b1;  
                    mem_write = 1'b0;  
                    alu_src = 1'b1;  
                    reg_write = 1'b1;  
                    sign_or_zero = 1'b1;  
                end  
                6'b101011: begin  // sw (Store Word)
                    reg_dst = 2'b00;  
                    mem_to_reg = 2'b00;  
                    alu_op = 2'b00;  
                    jump = 1'b0;  
                    branch = 1'b0;  
                    mem_read = 1'b0;  
                    mem_write = 1'b1;  
                    alu_src = 1'b1;  
                    reg_write = 1'b0;  
                    sign_or_zero = 1'b1;  
                end  
                6'b000100: begin  // beq (Branch if Equal)
                    reg_dst = 2'b00;  
                    mem_to_reg = 2'b00;  
                    alu_op = 2'b01;  
                    jump = 1'b0;  
                    branch = 1'b1;  
                    mem_read = 1'b0;  
                    mem_write = 1'b0;  
                    alu_src = 1'b0;  
                    reg_write = 1'b0;  
                    sign_or_zero = 1'b1;  
                end  
                6'b000010: begin  // j (Jump)
                    reg_dst = 2'b00; 
                    mem_to_reg = 2'b00;  
                    alu_op = 2'b11;  
                    jump = 1'b1;  
                    branch = 1'b0;  
                    mem_read = 1'b0;  
                    mem_write = 1'b0;  
                    alu_src = 1'b0;  
                    reg_write = 1'b0;  
                    sign_or_zero = 1'b1;  
                end  
                6'b000011: begin  
                    reg_dst = 2'b10; 
                    mem_to_reg = 2'b10;  
                    alu_op = 2'b00;  
                    jump = 1'b1;  
                    branch = 1'b0;  
                    mem_read = 1'b0;  
                    mem_write = 1'b0;  
                    alu_src = 1'b0;  
                    reg_write = 1'b1;  
                    sign_or_zero = 1'b1;  
                end  
                6'b001000: begin  // addi (Add Immediate)
                    reg_dst = 2'b00; 
                    mem_to_reg = 2'b00;  
                    alu_op = 2'b00;  
                    jump = 1'b0;  
                    branch = 1'b0;  
                    mem_read = 1'b0;  
                    mem_write = 1'b0;  
                    alu_src = 1'b1;  
                    reg_write = 1'b1;  
                    sign_or_zero = 1'b1;  
                end  
                default: begin  // Default (Caso para instrução inválida)
                    reg_dst = 2'b00;  
                    mem_to_reg = 2'b00;  
                    alu_op = 2'b00;  
                    jump = 1'b0;  
                    branch = 1'b0;  
                    mem_read = 1'b0;  
                    mem_write = 1'b0;  
                    alu_src = 1'b0;  
                    reg_write = 1'b0;  
                    sign_or_zero = 1'b1;  
                end  
            endcase  
        end  
    end  
endmodule

ThiagoMarcelMessias/mips_32.v
`include "ALU.v"
`include "DataMemory.v"
`include "ALUControl.v"
`include "MemoriaDeInstrucoes.v"
`include "Registradores.v"
`include "control.v"

module mips_32(
    input clk, reset,
    output [31:0] pc_out, alu_result
);
    reg [31:0] pc_current;  // Registrador para armazenar o valor do PC
    wire [31:0] pc_next, pc_plus_4;  
    wire [31:0] instr;  // Instrução de 32 bits
    wire [1:0] reg_dst, mem_to_reg; 
    wire [1:0] alu_op;  
    wire jump, branch, mem_read, mem_write, alu_src, reg_write;  
    wire [4:0] reg_write_dest;  
    wire [31:0] reg_write_data;  
    wire [4:0] reg_read_addr_1;  
    wire [31:0] reg_read_data_1;  
    wire [4:0] reg_read_addr_2;  
    wire [31:0] reg_read_data_2;  
    wire [31:0] sign_ext_im, read_data2, zero_ext_im, imm_ext;  
    wire JRControl;  
    wire [3:0] ALU_Control;  
    wire [31:0] ALU_out;  
    wire zero_flag;  
    wire [31:0] im_shift_1, PC_j, PC_beq, PC_jr;  
    wire [25:0] jump_shift_1;  
    wire [31:0] mem_read_data;  
    wire sign_or_zero;  

    // PC: Contador de programa
    always @(posedge clk or posedge reset) begin   
        if (reset)   
            pc_current <= 32'd0;  // Inicializa o PC com 0 no reset
        else  
            pc_current <= pc_next;  // Atualiza o PC com o próximo valor
    end  

    // PC + 4
    assign pc_plus_4 = pc_current + 32'd4;  

    // Memória de Instruções
    MemoriaDeInstrucoes instrucion_memory(
        .addr(pc_current),    // Endereço do contador de programa
        .instrucao(instr)     // A instrução lida da memória
    );  

    // Cálculo do Jump Shift
    assign jump_shift_1 = {instr[25:0], 2'b00};  

    // Unidade de controle
    control control_unit(
        .opcode(instr[31:26]), 
        .reset(reset), 
        .reg_dst(reg_dst),  
        .mem_to_reg(mem_to_reg), 
        .alu_op(alu_op), 
        .jump(jump),  
        .branch(branch), 
        .mem_read(mem_read),  
        .mem_write(mem_write),  
        .alu_src(alu_src),  
        .reg_write(reg_write),  
        .sign_or_zero(sign_or_zero)  // Seleção de sinal ou zero para extensão de imediato
    );  

    // Multiplexador para reg_dst
    assign reg_write_dest = (reg_dst == 2'b10) ? 5'b11111 :  // JAL
                            (reg_dst == 2'b01) ? instr[15:11] :  // R-type
                            instr[20:16];  // I-type  

    // Registradores
    assign reg_read_addr_1 = instr[25:21];  
    assign reg_read_addr_2 = instr[20:16];  
    Registradores reg_file(
        .RegWrite(reg_write),  
        .WriteRegister(reg_write_dest), 
        .WriteData(reg_write_data),  
        .ReadRegister1(reg_read_addr_1), 
        .ReadData1(reg_read_data_1),  
        .ReadRegister2(reg_read_addr_2), 
        .ReadData2(reg_read_data_2)  
    );  

    // Extensão de Imediato (Sign/Zero Extension)
    assign sign_ext_im = {{16{instr[15]}}, instr[15:0]};  
    assign zero_ext_im = {16'b0, instr[15:0]};  
    assign imm_ext = (sign_or_zero == 1'b1) ? sign_ext_im : zero_ext_im;  

    // Controle para JR
    assign JRControl = (instr[5:0] == 6'b001000);  

    // Controle da ALU
    ALUControl ALU_Control_unit(
        .ALUOp(alu_op), 
        .Func(instr[5:0]), 
        .ALU_Control(ALU_Control)
    );  

    // Multiplexador para ALU Src
    assign read_data2 = (alu_src == 1'b1) ? imm_ext : reg_read_data_2;  

    // Unidade ALU
    ALU alu_unit(
        .A(reg_read_data_1), 
        .B(read_data2), 
        .ALU_Control(ALU_Control),  
        .Result(ALU_out), 
        .Zero(zero_flag)
    );  

    // Shift de imediato
    assign im_shift_1 = {imm_ext[29:0], 2'b00};  

    // Cálculo do próximo PC
    assign PC_beq = pc_plus_4 + im_shift_1;  // Branch target
    assign PC_j = {pc_plus_4[31:28], jump_shift_1};  // Jump target
    assign PC_jr = reg_read_data_1;  // JR target

    // Determinação do próximo PC com base em branch, jump ou JR
    assign pc_next = (JRControl) ? PC_jr :  // JR
                     (branch & zero_flag) ? PC_beq :  // Branch
                     (jump) ? PC_j :  // Jump
                     pc_plus_4;  // PC + 4

    // Instância da memória de dados
    DataMemory data_mem (
        .clk(clk),
        .MemRead(mem_read),
        .MemWrite(mem_write),
        .address(ALU_out),  // Endereço da memória é a saída da ALU
        .writeData(reg_read_data_2),  
        .readData(mem_read_data)      
    );  

    // Multiplexador para mem_to_reg
    assign reg_write_data = (mem_to_reg == 2'b01) ? mem_read_data :  // LW
                            (mem_to_reg == 2'b10) ? pc_plus_4 :  // JAL
                            ALU_out;  // R-type ou I-type

    // Saídas
    assign pc_out = pc_current;
    assign alu_result = ALU_out;

endmodule

ThiagoMarcelMessias/tb_mips32.v
`include "mips_32.v"
`timescale 1ns / 1ps

module tb_mips_32();

    // Declaração de sinais de controle do processador
    reg clk, reset;
    wire [31:0] pc_out, alu_result;
    wire [31:0] instrucao;  // Nova variável para capturar a instrução lida

    // Instanciando o processador MIPS
    mips_32 mips_instance (
        .clk(clk),
        .reset(reset),
        .pc_out(pc_out),
        .alu_result(alu_result)
    );

    // Instância da memória de instruções
    MemoriaDeInstrucoes instrucion_memory (
        .addr(pc_out), // Endereço do PC (conectado ao pc_out)
        .instrucao(instrucao) // Passa a instrução para o processador
    );

    // Conectando a instrução lida ao sinal interno do processador
    assign mips_instance.instr = instrucao;

    // Gerando o clock e o reset
    initial begin
        clk = 0;
        reset = 1;
        
        // Aplicando o reset no início
        #10 reset = 0;  // Libera o reset após 10 unidades de tempo
    end

    // Gerando o sinal de clock
    always begin
        #5 clk = ~clk;  // Clock com período de 10 unidades de tempo
    end

    // Monitorando a execução da simulação
    initial begin
        // Monitorando o PC, ALU e a instrução lida
        $monitor("PC = %h, ALU Result = %h, Instruction = %h", pc_out, alu_result, instrucao);
            $dumpfile("mips_32_tb.vcd");  
        $dumpvars(0, tb_mips_32);
    end

    // Inicializando a simulação e passando o arquivo hex para a memória
    initial begin
        $readmemh("codigo.mem", instrucion_memory.memoria); // Carrega o arquivo "soma.hex" na memória de instruções
        
        // Rodando a simulação por um número de ciclos
        #100 $finish;  // Finaliza após 100 unidades de tempo (ajuste conforme necessário)
    end

endmodule

ThiagoMarcelMessias/mips_32_tb.vcd
$date
	Fri Apr 11 18:27:44 2025
$end
$version
	Icarus Verilog
$end
$timescale
	1ps
$end
$scope module tb_mips_32 $end
$var wire 32 ! pc_out [31:0] $end
$var wire 32 " instrucao [31:0] $end
$var wire 32 # alu_result [31:0] $end
$var reg 1 $ clk $end
$var reg 1 % reset $end
$scope module instrucion_memory $end
$var wire 32 & instrucao [31:0] $end
$var wire 32 ' addr [31:0] $end
$upscope $end
$scope module mips_instance $end
$var wire 32 ( PC_jr [31:0] $end
$var wire 32 ) alu_result [31:0] $end
$var wire 1 $ clk $end
$var wire 32 * instr [31:0] $end
$var wire 32 + pc_out [31:0] $end
$var wire 1 % reset $end
$var wire 1 , zero_flag $end
$var wire 32 - zero_ext_im [31:0] $end
$var wire 1 . sign_or_zero $end
$var wire 32 / sign_ext_im [31:0] $end
$var wire 5 0 reg_write_dest [4:0] $end
$var wire 32 1 reg_write_data [31:0] $end
$var wire 1 2 reg_write $end
$var wire 32 3 reg_read_data_2 [31:0] $end
$var wire 32 4 reg_read_data_1 [31:0] $end
$var wire 5 5 reg_read_addr_2 [4:0] $end
$var wire 5 6 reg_read_addr_1 [4:0] $end
$var wire 2 7 reg_dst [1:0] $end
$var wire 32 8 read_data2 [31:0] $end
$var wire 32 9 pc_plus_4 [31:0] $end
$var wire 32 : pc_next [31:0] $end
$var wire 1 ; mem_write $end
$var wire 2 < mem_to_reg [1:0] $end
$var wire 32 = mem_read_data [31:0] $end
$var wire 1 > mem_read $end
$var wire 26 ? jump_shift_1 [25:0] $end
$var wire 1 @ jump $end
$var wire 32 A imm_ext [31:0] $end
$var wire 32 B im_shift_1 [31:0] $end
$var wire 1 C branch $end
$var wire 1 D alu_src $end
$var wire 2 E alu_op [1:0] $end
$var wire 32 F PC_j [31:0] $end
$var wire 32 G PC_beq [31:0] $end
$var wire 1 H JRControl $end
$var wire 32 I ALU_out [31:0] $end
$var wire 4 J ALU_Control [3:0] $end
$var reg 32 K pc_current [31:0] $end
$scope module ALU_Control_unit $end
$var wire 6 L Func [5:0] $end
$var wire 2 M ALUOp [1:0] $end
$var wire 8 N ALUControlIn [7:0] $end
$var reg 4 O ALU_Control [3:0] $end
$upscope $end
$scope module alu_unit $end
$var wire 4 P ALU_Control [3:0] $end
$var wire 32 Q B [31:0] $end
$var wire 32 R A [31:0] $end
$var reg 32 S Result [31:0] $end
$var reg 1 , Zero $end
$upscope $end
$scope module control_unit $end
$var wire 6 T opcode [5:0] $end
$var wire 1 % reset $end
$var reg 2 U alu_op [1:0] $end
$var reg 1 D alu_src $end
$var reg 1 C branch $end
$var reg 1 @ jump $end
$var reg 1 > mem_read $end
$var reg 2 V mem_to_reg [1:0] $end
$var reg 1 ; mem_write $end
$var reg 2 W reg_dst [1:0] $end
$var reg 1 2 reg_write $end
$var reg 1 . sign_or_zero $end
$upscope $end
$scope module data_mem $end
$var wire 1 > MemRead $end
$var wire 1 ; MemWrite $end
$var wire 32 X address [31:0] $end
$var wire 1 $ clk $end
$var wire 32 Y writeData [31:0] $end
$var reg 32 Z readData [31:0] $end
$var integer 32 [ i [31:0] $end
$upscope $end
$scope module instrucion_memory $end
$var wire 32 \ addr [31:0] $end
$var wire 32 ] instrucao [31:0] $end
$upscope $end
$scope module reg_file $end
$var wire 32 ^ ReadData1 [31:0] $end
$var wire 32 _ ReadData2 [31:0] $end
$var wire 5 ` ReadRegister1 [4:0] $end
$var wire 5 a ReadRegister2 [4:0] $end
$var wire 1 2 RegWrite $end
$var wire 32 b WriteData [31:0] $end
$var wire 5 c WriteRegister [4:0] $end
$var wire 1 d clk $end
$var integer 32 e i [31:0] $end
$upscope $end
$upscope $end
$upscope $end
$enddefinitions $end
$comment Show the parameter values. $end
$dumpall
$end
#0
$dumpvars
b100000 e
zd
b1000 c
b0 b
b1000 a
b0 `
b0 _
b0 ^
b100000000010000000000000000101 ]
b0 \
b100000000 [
b0 Z
b0 Y
b0 X
b0 W
b0 V
b0 U
b1000 T
b0 S
b0 R
b0 Q
b10 P
b10 O
b101 N
b0 M
b101 L
b0 K
b10 J
b0 I
0H
b11000 G
b1000000000000000010100 F
b0 E
0D
0C
b10100 B
b101 A
0@
b1000000000000000010100 ?
0>
b0 =
b0 <
0;
b100 :
b100 9
b0 8
b0 7
b0 6
b1000 5
b0 4
b0 3
02
b0 1
b1000 0
b101 /
1.
b101 -
1,
b0 +
b100000000010000000000000000101 *
b0 )
b0 (
b0 '
b100000000010000000000000000101 &
1%
0$
b0 #
b100000000010000000000000000101 "
b0 !
$end
#5000
1$
#10000
b101 1
b101 b
0,
b101 #
b101 )
b101 I
b101 S
b101 X
b101 8
b101 Q
12
1D
0$
0%
#15000
b1010 1
b1010 b
b1010 #
b1010 )
b1010 I
b1010 S
b1010 X
b1001 0
b1001 c
b1010 8
b1010 Q
b101000 B
b1000 :
b1001000000000000101000 F
b1001000000000000101000 ?
b1010 A
b1001 5
b1001 a
b1010 /
b1010 -
b1010 N
b1010 L
b100000000010010000000000001010 *
b100000000010010000000000001010 ]
b100000000010010000000000001010 "
b100000000010010000000000001010 &
b110000 G
b1000 9
b100 !
b100 '
b100 +
b100 K
b100 \
1$
#20000
0$
#25000
1,
b0 #
b0 )
b0 I
b0 S
b0 X
b0 1
b0 b
b1000 0
b1000 c
b0 8
b0 Q
b0 B
b1100 :
b1000000000000000000000 F
b1000000000000000000000 ?
1>
b1 <
b1 V
b0 A
b100011 T
b1000 5
b1000 a
b0 /
b0 -
b0 N
b0 L
b10001100000010000000000000000000 *
b10001100000010000000000000000000 ]
b10001100000010000000000000000000 "
b10001100000010000000000000000000 &
b1100 G
b1100 9
b1000 !
b1000 '
b1000 +
b1000 K
b1000 \
1$
#30000
0$
#35000
0,
b100 #
b100 )
b100 I
b100 S
b100 X
b1001 0
b1001 c
b100 8
b100 Q
b10000 B
b10000 :
b1001000000000000010000 F
b1001000000000000010000 ?
b100 A
b1001 5
b1001 a
b100 /
b100 -
b100 N
b100 L
b10001100000010010000000000000100 *
b10001100000010010000000000000100 ]
b10001100000010010000000000000100 "
b10001100000010010000000000000100 &
b100000 G
b10000 9
b1100 !
b1100 '
b1100 +
b1100 K
b1100 \
1$
#40000
0$
#45000
1,
b1000 0
b1000 c
b0 #
b0 )
b0 I
b0 S
b0 X
b0 1
b0 b
b0 8
b0 Q
b10000000010000000 B
b10100 :
b1001010000000010000000 F
b1001010000000010000000 ?
0D
0>
b10 E
b10 M
b10 U
b0 <
b0 V
b1 7
b1 W
b100000000100000 A
b0 T
b1000 6
b1000 `
b100000000100000 /
b100000000100000 -
b10100000 N
b100000 L
b1000010010100000000100000 *
b1000010010100000000100000 ]
b1000010010100000000100000 "
b1000010010100000000100000 &
b10000000010010100 G
b10100 9
b10000 !
b10000 '
b10000 +
b10000 K
b10000 \
1$
#50000
0$
#55000
bx 1
bx b
bx 0
bx c
bx00 B
b0xxxxxxxxxxxxxxxxxxxxxxxx00 F
bx00 ?
02
b0 E
b0 M
b0 U
b0 7
b0 W
x,
bx #
bx )
bx I
bx S
bx X
bx 8
bx Q
bx A
bx :
bx T
bx (
bx 4
bx R
bx ^
bx 6
bx `
bx 3
bx Y
bx _
bx 5
bx a
bx /
b0xxxxxxxxxxxxxxxx -
xH
b0xxxxxx N
bx L
bx *
bx ]
bx "
bx &
bx G
b11000 9
b10100 !
b10100 '
b10100 +
b10100 K
b10100 \
1$
#60000
0$
#65000
b0xxxxxxxxxxxxxxxxxxxxxxxxxxxx00 F
bx 9
bx !
bx '
bx +
bx K
bx \
1$
