DaviCosta/Processador.v
module ALU(
    input [31:0] A,
    input [31:0] B,
    input [3:0] Controle_ALU,
    output reg [31:0] resultado,
    output zero
);
    always @(*) begin
        case(Controle_ALU)
            4'b0000: resultado = A & B;           // and
            4'b0001: resultado = A | B;           // or
            4'b0010: resultado = A + B;           // soma
            4'b0110: resultado = A - B;           // subtração
            4'b0111: resultado = (A < B) ? 32'b1 : 32'b0; // slt
            default: resultado = 32'b0;           // caso inválido
        endcase
    end
    assign zero = (resultado == 32'b0);
endmodule

module MUX(
    input [31:0] A,
    input [31:0] B,
    input seletor,
    output [31:0] saida
);
    assign saida = (seletor) ? A : B;
endmodule

module Registrador(
    input clk,
    input reset,        //sinal de reset para inicialização
    input [4:0] rs,     //endereço do registrador rs
    input [4:0] rt,     //endereço do registrador rt
    input [4:0] rd,     //endereço do registrador rd (destino)
    input [31:0] wd,    //dado a ser escritovindo do MUX
    input rw,           //sinal de escrita, 1 para escrever em rd
    output [31:0] read_data1,   //valor lido de rs
    output [31:0] read_data2    //valor lido de rt
);
    reg [31:0] registradores [31:0]; //banco de 32 registradores de 32 bits

    //aqui está lendo os dados para serem usados nas operações
    assign read_data1 = registradores[rs];
    assign read_data2 = registradores[rt];

    //iniciando os registradores
    integer i;
    always @(posedge clk or posedge reset) begin
        if(reset) begin
            //reset inicializa todos os registradores com 0
            for (i = 0; i < 32; i = i + 1)
                registradores[i] <= 32'b0;
        end
        //escrita normal, se rw está ativo e rd não é o registrador 0
        if (rw && (rd != 0))
            registradores[rd] <= wd;
    end
endmodule

module Unidade_controle(
    input [5:0] opcode,
    output reg rw,
    output reg alu_src,
    output reg mw,
    output reg mtr,
    output reg branch,
    output reg jump,
    output reg [1:0] alu_op
);

    //a unidade de controle decodifica o opcode da instrução e gera os sinais de controle correspondentes
    //para determinar o comportamento da ALU, dos registradores e da memória. Os sinais são definidos com base 
    //na instrução e controla as operações de leitura ou escrita e a manipulação de dados
    always @(*) begin
        rw = 1'b0;
        alu_src = 1'b0;
        mw = 1'b0;
        mtr = 1'b0;
        branch = 1'b0;
        jump = 1'b0;
        alu_op = 2'b00;
        
        case (opcode)
            6'b000000: begin    //instrução R-type
                rw = 1'b1;      //habilita a escrita no registrador de destino
                alu_src = 1'b0; //a alu opera usando dois registradores
                alu_op = 2'b10; //determina a operação da alu
            end
            6'b100011: begin    //lw
                rw = 1'b1;
                alu_src = 1'b1;
                mtr = 1'b1;
                alu_op = 2'b00; //a ALU faz uma soma para calcular o endereço
            end
            6'b101011: begin    //sw
                alu_src = 1'b1;
                mw = 1'b1;      //permite escrita de memoria
                alu_op = 2'b00; //soma para o endereço
            end
            6'b000100: begin    //beq
                branch = 1'b1;
                alu_op = 2'b01; //subtração para comparação
            end
            6'b000010: begin    //jump
                jump = 1'b1;
            end
            default: begin //se o opcode não corresponder a nenhuma instrução conhecida tudo continua zero
                rw      = 1'b0;
                alu_src = 1'b0;
                mw      = 1'b0;
                mtr     = 1'b0;
                branch  = 1'b0;
                jump    = 1'b0;
                alu_op  = 2'b00;
            end
        endcase
    end
endmodule

module ALU_CONTROLE(
    input [5:0] funcao,
    input [1:0] alu_op,
    output reg [3:0] alu_controle
);
    always @(*) begin
        case(alu_op)
            2'b00: alu_controle = 4'b0010;  //lw e sw - adição
            2'b01: alu_controle = 4'b0110;  //beq - subtração
            2'b10: begin
                case (funcao)
                    6'b100000: alu_controle = 4'b0010;  // add
                    6'b100010: alu_controle = 4'b0110;  // sub
                    6'b100100: alu_controle = 4'b0000;  // and
                    6'b100101: alu_controle = 4'b0001;  // or
                    6'b101010: alu_controle = 4'b0111;  // slt
                    default: alu_controle = 4'b0000;
                endcase
            end
            default: alu_controle = 4'b0000; //caso inválido
        endcase
    end
endmodule

module Instrucao_memoria(
    input [31:0] endereco,
    output [31:0] instrucao
);
    reg [31:0] mem [0:255];
    initial begin
        $readmemb("codigoprocessador.bin", mem); //ler arquivo em assembly
    end
    assign instrucao = mem[endereco[9:2]];
endmodule

module Data(
    input clk,
    input reset,
    input [31:0] endereco,
    input [31:0] wd,
    input mw,
    output [31:0] rd
);
    reg [31:0] mem [0:255]; //essa memoria serve para guardar os arquivos para continuar a instrução quando se passar um ciclo no processador
    integer i;
    initial begin
        for(i = 0; i < 29; i = i+1)
            mem[i] = 32'b0;
    end

    //durante o ciclo de clock, se o sinal de controle mw estiver ativado, 
    //wd será escrito na memória no endereço especificado por endereco[9:2]
    //o endereço é truncado para 8 bits (9:2) para acessar a posição correta na memória
    //o dado lido da memória na posição endereco[9:2] é atribuído ao sinal rd
    always @(posedge clk or posedge reset) begin
        if(reset) begin
            for (i = 0; i < 256; i=i+1) begin
                mem[i] <= 32'b0;
            end
        end
        else if(mw)
            mem[endereco[9:2]] <= wd;
    end
    assign rd = mem[endereco[9:2]];
endmodule

module Processador_MIPS (
    input clk,
    input reset
);
    reg [31:0] pc;
    wire [31:0] instrucao;
    wire [31:0] read_data1;
    wire [31:0] read_data2;
    wire [31:0] alu_resultado;
    wire [31:0] mem_data;
    wire [31:0] sinal_extendido;
    wire [31:0] wd;
    wire [3:0] alu_controle;
    wire zero;
    
    wire rw, alu_src, mw, mtr, branch, jump;
    wire [1:0] alu_op;
    
    wire [31:0] alu_input2;
    wire [31:0] pc_next;
    
    Instrucao_memoria imem(
        .endereco(pc),
        .instrucao(instrucao)
    );
    
    //essa extensão de sinal preserva o sinal do valor imediato, garantindo que ele continue sendo negativo ou positivo
    assign sinal_extendido = {{16{instrucao[15]}}, instrucao[15:0]};
    
    Registrador reg_file(
        .clk(clk),
        .rs(instrucao[25:21]),
        .rt(instrucao[20:16]),
        .rd(instrucao[15:11]),
        .wd(wd),
        .rw(rw),
        .read_data1(read_data1),
        .read_data2(read_data2)
    );
    
    Unidade_controle controle(
        .opcode(instrucao[31:26]),
        .rw(rw),
        .alu_src(alu_src),
        .mw(mw),
        .mtr(mtr),
        .branch(branch),
        .jump(jump),
        .alu_op(alu_op)
    );
    
    ALU_CONTROLE alu_ctrl_inst(
        .funcao(instrucao[5:0]),
        .alu_op(alu_op),
        .alu_controle(alu_controle)
    );
    
    MUX mux_alu_src(
        .A(sinal_extendido),
        .B(read_data2),
        .seletor(alu_src),
        .saida(alu_input2)
    );
    
    ALU alu(
        .A(read_data1),
        .B(alu_input2),
        .Controle_ALU(alu_controle),
        .resultado(alu_resultado),
        .zero(zero)
    );
    
    Data dmem(
        .clk(clk),
        .endereco(alu_resultado),
        .wd(read_data2),
        .mw(mw),
        .rd(mem_data)
    );
    
    MUX mux_mem_para_reg(
        .A(mem_data),
        .B(alu_resultado),
        .seletor(mtr),
        .saida(wd)
    );
    
    //aqui vai haver a comparação para ver se o processador irá dar um jump ou continuar para a proxima instrução
    //próxima instrução de PC, lida com jump e branchs 
    assign pc_next = (jump) ? 
        {pc[31:28], instrucao[25:0], 2'b00} : 
        ((branch & zero) ? (pc + 4 + (sinal_extendido << 2)) : (pc + 4));
    
    //atualização do PC com reset
    always @(posedge clk or posedge reset) begin
        if(reset)
            pc <= 32'b0;
        else
            pc <= pc_next;
    end
endmodule

DaviCosta/tb_processador_mips.v
`timescale 1ns/1ps
module tb_processador_mips;
    reg clk;
    reg reset;
    
    // Instancia o processador MIPS
    Processador_MIPS uut (
        .clk(clk),
        .reset(reset)
    );
    
    // Geração do clock: período de 10ns
    initial begin
        clk = 0;
        forever #5 clk = ~clk;
    end
    
    // Sequência de reset e término da simulação
    initial begin
        reset = 1;
        #15;       // Mantém o reset ativo por alguns ciclos
        reset = 0;
        #500;      // Ajuste o tempo de simulação conforme necessário
        $finish;
    end
    
    // Gerar arquivo de waveform (VCD) para visualizar com GTKWave
    initial begin
        $dumpfile("simulation.vcd");
        $dumpvars(0, tb_processador_mips);
    end
    
    // Monitoramento dos sinais chave: PC e instrução atual
    initial begin
        $monitor("Time=%0t | PC=%h | Instr=%h", $time, uut.pc, uut.instrucao);
    end
endmodule

DaviCosta/simulation.vcd
$date
	Fri Feb 14 06:47:16 2025
$end
$version
	Icarus Verilog
$end
$timescale
	1ps
$end
$scope module tb_processador_mips $end
$var reg 1 ! clk $end
$var reg 1 " reset $end
$scope module uut $end
$var wire 1 ! clk $end
$var wire 1 " reset $end
$var wire 1 # zero $end
$var wire 32 $ wd [31:0] $end
$var wire 32 % sinal_extendido [31:0] $end
$var wire 1 & rw $end
$var wire 32 ' read_data2 [31:0] $end
$var wire 32 ( read_data1 [31:0] $end
$var wire 32 ) pc_next [31:0] $end
$var wire 1 * mw $end
$var wire 1 + mtr $end
$var wire 32 , mem_data [31:0] $end
$var wire 1 - jump $end
$var wire 32 . instrucao [31:0] $end
$var wire 1 / branch $end
$var wire 1 0 alu_src $end
$var wire 32 1 alu_resultado [31:0] $end
$var wire 2 2 alu_op [1:0] $end
$var wire 32 3 alu_input2 [31:0] $end
$var wire 4 4 alu_controle [3:0] $end
$var reg 32 5 pc [31:0] $end
$scope module alu $end
$var wire 1 # zero $end
$var wire 4 6 Controle_ALU [3:0] $end
$var wire 32 7 B [31:0] $end
$var wire 32 8 A [31:0] $end
$var reg 32 9 resultado [31:0] $end
$upscope $end
$scope module alu_ctrl_inst $end
$var wire 6 : funcao [5:0] $end
$var wire 2 ; alu_op [1:0] $end
$var reg 4 < alu_controle [3:0] $end
$upscope $end
$scope module controle $end
$var wire 6 = opcode [5:0] $end
$var reg 2 > alu_op [1:0] $end
$var reg 1 0 alu_src $end
$var reg 1 / branch $end
$var reg 1 - jump $end
$var reg 1 + mtr $end
$var reg 1 * mw $end
$var reg 1 & rw $end
$upscope $end
$scope module dmem $end
$var wire 1 ! clk $end
$var wire 32 ? endereco [31:0] $end
$var wire 1 * mw $end
$var wire 32 @ rd [31:0] $end
$var wire 1 A reset $end
$var wire 32 B wd [31:0] $end
$var integer 32 C i [31:0] $end
$upscope $end
$scope module imem $end
$var wire 32 D endereco [31:0] $end
$var wire 32 E instrucao [31:0] $end
$upscope $end
$scope module mux_alu_src $end
$var wire 32 F A [31:0] $end
$var wire 1 0 seletor $end
$var wire 32 G saida [31:0] $end
$var wire 32 H B [31:0] $end
$upscope $end
$scope module mux_mem_para_reg $end
$var wire 32 I A [31:0] $end
$var wire 32 J B [31:0] $end
$var wire 1 + seletor $end
$var wire 32 K saida [31:0] $end
$upscope $end
$scope module reg_file $end
$var wire 1 ! clk $end
$var wire 5 L rd [4:0] $end
$var wire 32 M read_data1 [31:0] $end
$var wire 32 N read_data2 [31:0] $end
$var wire 1 O reset $end
$var wire 5 P rs [4:0] $end
$var wire 5 Q rt [4:0] $end
$var wire 1 & rw $end
$var wire 32 R wd [31:0] $end
$var integer 32 S i [31:0] $end
$upscope $end
$upscope $end
$upscope $end
$enddefinitions $end
$comment Show the parameter values. $end
$dumpall
$end
#0
$dumpvars
bx S
bx R
b1000 Q
b0 P
zO
bx N
bx M
b0 L
bx K
bx J
bx I
bx H
bx G
b10 F
b100100000010000000000000000010 E
b0 D
b11101 C
bx B
zA
bx @
bx ?
b0 >
b1001 =
b10 <
b0 ;
b10 :
bx 9
bx 8
bx 7
b10 6
b0 5
b10 4
bx 3
b0 2
bx 1
00
0/
b100100000010000000000000000010 .
0-
bx ,
0+
0*
b100 )
bx (
bx '
0&
b10 %
bx $
x#
1"
0!
$end
#5000
1!
#10000
0!
#15000
b1000 )
b11 :
b1001 Q
b11 %
b11 F
b100100000010010000000000000011 .
b100100000010010000000000000011 E
b100 5
b100 D
1!
0"
#20000
0!
#25000
b10 2
b10 ;
b10 >
1&
b1100 )
b100000 :
b0 =
b1010 L
b1000 P
b101000000100000 %
b101000000100000 F
b1000010010101000000100000 .
b1000010010101000000100000 E
b1000 5
b1000 D
1!
#30000
0!
#35000
b0 2
b0 ;
b0 >
0&
b10000 )
b1010 :
b1001 =
b0 L
b1011 Q
b0 P
b1010 %
b1010 F
b100100000010110000000000001010 .
b100100000010110000000000001010 E
b1100 5
b1100 D
1!
#40000
0!
#45000
b10100 )
b100 :
b1100 Q
b100 %
b100 F
b100100000011000000000000000100 .
b100100000011000000000000000100 E
b10000 5
b10000 D
1!
#50000
0!
#55000
b110 4
b110 6
b110 <
b10 2
b10 ;
b10 >
1&
b11000 )
b100010 :
b0 =
b1101 L
b1011 P
b110100000100010 %
b110100000100010 F
b1011011000110100000100010 .
b1011011000110100000100010 E
b10100 5
b10100 D
1!
#60000
0!
#65000
b10 4
b10 6
b10 <
b0 2
b0 ;
b0 >
0&
b11100 )
b0 :
b1111 =
b11111 L
b1 Q
b0 P
b11111111111111111111111100000000 %
b11111111111111111111111100000000 F
b111100000000011111111100000000 .
b111100000000011111111100000000 E
b11000 5
b11000 D
1!
#70000
0!
#75000
b100000 )
b1101 =
b1110 Q
b1 P
b110100001011101111111100000000 .
b110100001011101111111100000000 E
b11100 5
b11100 D
1!
#80000
0!
#85000
b100100 )
b111111 :
b1111 =
b0 L
b1 Q
b0 P
b11111111 %
b11111111 F
b111100000000010000000011111111 .
b111100000000010000000011111111 E
b100000 5
b100000 D
1!
#90000
0!
#95000
b101000 )
b1101 =
b1111 Q
b1 P
b110100001011110000000011111111 .
b110100001011110000000011111111 E
b100100 5
b100100 D
1!
#100000
0!
#105000
b0 4
b0 6
b0 <
b10 2
b10 ;
b10 >
1&
b101100 )
b100100 :
b0 =
b11000 L
b1110 P
b11111111111111111100000000100100 %
b11111111111111111100000000100100 F
b1110011111100000000100100 .
b1110011111100000000100100 E
b101000 5
b101000 D
1!
#110000
0!
#115000
b1 4
b1 6
b1 <
b110000 )
b100101 :
b11001 L
b11111111111111111100100000100101 %
b11111111111111111100100000100101 F
b1110011111100100000100101 .
b1110011111100100000100101 E
b101100 5
b101100 D
1!
#120000
0!
#125000
b10 4
b10 6
b10 <
b0 2
b0 ;
b0 >
0&
b110100 )
b1 :
b1001 =
b0 L
b10000 Q
b0 P
b1 %
b1 F
b100100000100000000000000000001 .
b100100000100000000000000000001 E
b110000 5
b110000 D
1!
#130000
0!
#135000
b111000 )
b10 :
b10001 Q
b10 %
b10 F
b100100000100010000000000000010 .
b100100000100010000000000000010 E
b110100 5
b110100 D
1!
#140000
0!
#145000
b0 ,
b0 @
b0 I
b0x $
b0x K
b0x R
b0x 1
b0x 9
b0x ?
b0x J
b111 4
b111 6
b111 <
b10 2
b10 ;
b10 >
1&
b111100 )
b101010 :
b0 =
b10010 L
b10000 P
b11111111111111111001000000101010 %
b11111111111111111001000000101010 F
b10000100011001000000101010 .
b10000100011001000000101010 E
b111000 5
b111000 D
1!
#150000
0!
#155000
bx ,
bx @
bx I
bx $
bx K
bx R
bx 1
bx 9
bx ?
bx J
b10 4
b10 6
b10 <
b0 2
b0 ;
b0 >
0&
b1000000 )
b1 :
b1111 =
b10 L
b1 Q
b0 P
b1000000000001 %
b1000000000001 F
b111100000000010001000000000001 .
b111100000000010001000000000001 E
b111100 5
b111100 D
1!
#160000
0!
#165000
b1000100 )
b0 :
b1101 =
b0 L
b10100 Q
b1 P
b0 %
b0 F
b110100001101000000000000000000 .
b110100001101000000000000000000 E
b1000000 5
b1000000 D
1!
#170000
0!
#175000
b0 3
b0 7
b0 G
1+
10
1&
b1001000 )
b100011 =
b10011 Q
b10100 P
b10001110100100110000000000000000 .
b10001110100100110000000000000000 E
b1000100 5
b1000100 D
1!
#180000
0!
#185000
0+
00
0&
bx 3
bx 7
bx G
b1001100 )
b1 :
b1111 =
b10 L
b1 Q
b0 P
b1000000000001 %
b1000000000001 F
b111100000000010001000000000001 .
b111100000000010001000000000001 E
b1001000 5
b1001000 D
1!
#190000
0!
#195000
b1010000 )
b10000 :
b1101 =
b0 L
b10101 Q
b1 P
b10000 %
b10000 F
b110100001101010000000000010000 .
b110100001101010000000000010000 E
b1001100 5
b1001100 D
1!
#200000
0!
#205000
b0 3
b0 7
b0 G
1*
10
b1010100 )
b0 :
b101011 =
b10011 Q
b10101 P
b0 %
b0 F
b10101110101100110000000000000000 .
b10101110101100110000000000000000 E
b1010000 5
b1010000 D
1!
#210000
0!
#215000
b110 4
b110 6
b110 <
b1 2
b1 ;
b1 >
1/
0*
00
bx 3
bx 7
bx G
b1011x00 )
b1 :
b100 =
b1000 Q
b1000 P
b1 %
b1 F
b10001000010000000000000000001 .
b10001000010000000000000000001 E
b1010100 5
b1010100 D
1!
#220000
0!
#225000
b10 4
b10 6
b10 <
b0 2
b0 ;
b0 >
0/
bx )
bx :
bx =
bx L
bx Q
bx P
bx %
bx F
bx .
bx E
b1011x00 5
b1011x00 D
1!
#230000
0!
#235000
bx 5
bx D
1!
