LincolnDaSilva/jump_unit.v
module jump_unit(
    input wire [25:0] jumpAddr,
    input wire [31:0] pcAtual,
    output wire [31:0] jumpAddress
);

    assign jumpAddress = {pcAtual[31:28], jumpAddr, 2'b00};

endmodule

LincolnDaSilva/unidade_controle.v
module unidade_controle(
    input wire [5:0] opcode,
    input wire [5:0] funct,
    output reg RegWrite,
    output reg [3:0] ALUOperation,
    output reg MemWrite,
    output reg [1:0] pcSrc,
    output reg ALUSrc,
    output reg RegDst
);

    always @(*) begin
        case (opcode)
            6'b000000: begin // Instruções do tipo R
                RegWrite = 1'b1;
                MemWrite = 1'b0;
                ALUSrc = 1'b0;
                RegDst = 1'b1;
                pcSrc = 2'b00;
                case (funct)
                    6'b100000: ALUOperation = 4'b0010; // ADD
                    6'b100010: ALUOperation = 4'b0110; // SUB
                    6'b100100: ALUOperation = 4'b0000; // AND
                    6'b100101: ALUOperation = 4'b0001; // OR
                    6'b101010: ALUOperation = 4'b0111; // SLT
                    default: ALUOperation = 4'b0000;   // Operação inválida
                endcase
            end
            6'b100011: begin // LW (Load Word)
                RegWrite = 1'b1;
                MemWrite = 1'b0;
                ALUSrc = 1'b1;
                RegDst = 1'b0;
                pcSrc = 2'b00;
                ALUOperation = 4'b0010; // ADD (para calcular o endereço)
            end
            6'b101011: begin // SW (Store Word)
                RegWrite = 1'b0;
                MemWrite = 1'b1;
                ALUSrc = 1'b1;
                RegDst = 1'b0;
                pcSrc = 2'b00;
                ALUOperation = 4'b0010; // ADD (para calcular o endereço)
            end
            6'b000100: begin // BEQ (Branch if Equal)
                RegWrite = 1'b0;
                MemWrite = 1'b0;
                ALUSrc = 1'b0;
                RegDst = 1'b0;
                pcSrc = 2'b01; // Seleciona branchAddress
                ALUOperation = 4'b0110; // SUB (para comparar registradores)
            end
            6'b000010: begin // J (Jump)
                RegWrite = 1'b0;
                MemWrite = 1'b0;
                ALUSrc = 1'b0;
                RegDst = 1'b0;
                pcSrc = 2'b10; // Seleciona jumpAddress
                ALUOperation = 4'b0000; // Operação irrelevante
            end
            default: begin // Instrução inválida
                RegWrite = 1'b0;
                MemWrite = 1'b0;
                ALUSrc = 1'b0;
                RegDst = 1'b0;
                pcSrc = 2'b00;
                ALUOperation = 4'b0000;
            end
        endcase
    end

endmodule

LincolnDaSilva/memoria_dados.v
module memoria_dados(
    input wire clk,
    input wire [31:0] addr,
    input wire [31:0] WriteData,
    input wire MemWrite,
    output wire [31:0] ReadData
);

    reg [31:0] memoria [255:0];

    // Leitura combinacional
    assign ReadData = memoria[addr[9:2]];

    // Escrita síncrona
    always @(posedge clk) begin
        if (MemWrite) begin
            memoria[addr[9:2]] <= WriteData;
        end
    end

endmodule

LincolnDaSilva/alu.v
module alu(
    input wire [31:0] A,
    input wire [31:0] B,
    input wire [3:0] ALUOperation,
    output reg [31:0] ALUResult,
    output wire Zero
);

    always @(*) begin
        case (ALUOperation)
            4'b0000: ALUResult = A & B;       // AND
            4'b0001: ALUResult = A | B;       // OR
            4'b0010: ALUResult = A + B;       // ADD
            4'b0110: ALUResult = A - B;       // SUB
            4'b0111: ALUResult = (A < B) ? 1 : 0; // SLT
            4'b1100: ALUResult = ~(A | B);    // NOR
            default: ALUResult = 32'b0;       // Operação inválida
        endcase
    end

    assign Zero = (ALUResult == 32'b0);

endmodule

LincolnDaSilva/registradores.v
module registradores(
    input wire clk,
    input wire [4:0] ReadRegister1,
    input wire [4:0] ReadRegister2,
    input wire [4:0] WriteRegister,
    input wire [31:0] WriteData,
    input wire RegWrite,
    output wire [31:0] ReadData1,
    output wire [31:0] ReadData2
);

    reg [31:0] registers [31:0];

    // Inicialização dos registradores
    integer i;
    initial begin
        for (i = 0; i < 32; i = i + 1) begin
            registers[i] = 32'b0;
        end
    end

    // Leitura combinacional
    assign ReadData1 = registers[ReadRegister1];
    assign ReadData2 = registers[ReadRegister2];

    // Escrita síncrona
    always @(posedge clk) begin
        if (RegWrite && WriteRegister != 5'b0) begin
            registers[WriteRegister] <= WriteData;
        end
    end

endmodule

LincolnDaSilva/memoria_instrucoes.v
module memoria_instrucoes(
    input wire [31:0] addr,        // Endereço da instrução
    output wire [31:0] instrucao   // Instrução lida
);

    // Memória de instruções (256 palavras de 32 bits)
    reg [31:0] memoria [255:0];

    // Inicialização da memória
    integer i; // Corrigido: "1" foi substituído por "i"
    initial begin
        memoria[0] = 32'h20080001;  // addi $t0, $zero, 1
        memoria[1] = 32'h20090002;  // addi $t1, $zero, 2
        memoria[2] = 32'h01095020;  // add $t2, $t0, $t1
        memoria[3] = 32'hAC0A0000;  // sw $t2, 0($zero)
        for (i = 4; i < 256; i = i + 1) begin
            memoria[i] = 32'b0;     // Zera o restante da memória.
        end
    end

    // Leitura combinacional
    assign instrucao = memoria[addr[9:2]]; // Usa os bits 9:2 para indexar (alinhado em palavras)

endmodule

LincolnDaSilva/fetch_unit.v
module fetch_unit(
    input wire clk,
    input wire reset,
    input wire [31:0] branchAddress,
    input wire [31:0] jumpAddress,
    input wire [1:0] pcSrc,
    output wire [31:0] instrucao,
    output wire [31:0] pcAtual
);

    reg [31:0] pc;

    // Instância da Memória de Instruções
    memoria_instrucoes mem_inst (
        .addr(pc),
        .instrucao(instrucao)
    );

    // Lógica do PC
    always @(posedge clk or posedge reset) begin
        if (reset) begin
            pc <= 32'b0;
        end else begin
            case (pcSrc)
                2'b00: pc <= pc + 4;             // Próxima instrução sequencial
                2'b01: pc <= branchAddress;      // Branch
                2'b10: pc <= jumpAddress;        // Jump
                default: pc <= pc + 4;
            endcase
        end
    end

    assign pcAtual = pc;

endmodule

LincolnDaSilva/mips_cpu.v
module mips_cpu (
    input wire clk,
    input wire reset,
    output wire [31:0] pcAtual // 
);

// Sinais internos
wire [31:0] instrucao, ReadData1, ReadData2, ALUResult, WriteData, ReadDataMem;
wire [3:0] ALUOperation;
wire RegWrite, MemWrite, ALUSrc, RegDst, Zero;
wire [1:0] pcSrc;
wire [31:0] branchAddress, jumpAddress;

// Instância do Fetch Unit
fetch_unit fetch (
    .clk(clk),
    .reset(reset),
    .branchAddress(branchAddress),
    .jumpAddress(jumpAddress),
    .pcSrc(pcSrc),
    .instrucao(instrucao),
    .pcAtual(pcAtual)
);

// Instância do Banco de Registradores
registradores regs (
    .clk(clk),
    .ReadRegister1(instrucao[25:21]),
    .ReadRegister2(instrucao[20:16]),
    .WriteRegister(RegDst ? instrucao[15:11] : instrucao[20:16]),
    .WriteData(WriteData),
    .RegWrite(RegWrite),
    .ReadData1(ReadData1),
    .ReadData2(ReadData2)
);

// Instância da ALU
alu alu (
    .A(ReadData1),
    .B(ALUSrc ? instrucao[15:0] : ReadData2),
    .ALUOperation(ALUOperation),
    .ALUResult(ALUResult),
    .Zero(Zero)
);

// Instância da Memória de Dados
memoria_dados data_mem (
    .clk(clk),
    .addr(ALUResult),
    .WriteData(ReadData2),
    .MemWrite(MemWrite),
    .ReadData(ReadDataMem)
);

// Instância da Unidade de Controle
unidade_controle control (
    .opcode(instrucao[31:26]),
    .funct(instrucao[5:0]),
    .RegWrite(RegWrite),
    .ALUOperation(ALUOperation),
    .MemWrite(MemWrite),
    .pcSrc(pcSrc),
    .ALUSrc(ALUSrc),
    .RegDst(RegDst)
);

// Instância do Jump Unit
jump_unit jump (
    .jumpAddr(instrucao[25:0]),
    .pcAtual(pcAtual),
    .jumpAddress(jumpAddress)
);

// Lógica para branchAddress
assign branchAddress = pcAtual + (instrucao[15:0] << 2);

// Lógica para WriteData
assign WriteData = (MemWrite) ? ReadDataMem : ALUResult;

endmodule

LincolnDaSilva/tb_mips_cpu.v
module tb_mips_cpu;

    reg clk, reset;
    wire [31:0] pcAtual;  // Sinal de saída do PC

    // Instância do mips_cpu
    mips_cpu uut (
        .clk(clk),
        .reset(reset),
        .pcAtual(pcAtual)  // Conectando o sinal de PC
    );

    // Gerador de clock
    always #5 clk = ~clk;

    // Inicialização
    initial begin
        clk = 0;
        reset = 1;
        #10 reset = 0;
        #100 $finish;  // Finaliza a simulação após 100 unidades de tempo
    end

    // Dump de forma de onda
    initial begin
        $dumpfile("waveform.vcd");
        $dumpvars(0, tb_mips_cpu);  // Captura todos os sinais no módulo de teste
    end

endmodule

LincolnDaSilva/waveform.vcd
$date
	Fri Feb 07 13:56:16 2025
$end
$version
	Icarus Verilog
$end
$timescale
	1s
$end
$scope module tb_mips_cpu $end
$var wire 32 ! pcAtual [31:0] $end
$var reg 1 " clk $end
$var reg 1 # reset $end
$scope module uut $end
$var wire 1 " clk $end
$var wire 1 # reset $end
$var wire 2 $ pcSrc [1:0] $end
$var wire 32 % pcAtual [31:0] $end
$var wire 32 & jumpAddress [31:0] $end
$var wire 32 ' instrucao [31:0] $end
$var wire 32 ( branchAddress [31:0] $end
$var wire 1 ) Zero $end
$var wire 32 * WriteData [31:0] $end
$var wire 1 + RegWrite $end
$var wire 1 , RegDst $end
$var wire 32 - ReadDataMem [31:0] $end
$var wire 32 . ReadData2 [31:0] $end
$var wire 32 / ReadData1 [31:0] $end
$var wire 1 0 MemWrite $end
$var wire 1 1 ALUSrc $end
$var wire 32 2 ALUResult [31:0] $end
$var wire 4 3 ALUOperation [3:0] $end
$scope module alu $end
$var wire 32 4 B [31:0] $end
$var wire 1 ) Zero $end
$var wire 4 5 ALUOperation [3:0] $end
$var wire 32 6 A [31:0] $end
$var reg 32 7 ALUResult [31:0] $end
$upscope $end
$scope module control $end
$var wire 6 8 funct [5:0] $end
$var wire 6 9 opcode [5:0] $end
$var reg 4 : ALUOperation [3:0] $end
$var reg 1 1 ALUSrc $end
$var reg 1 0 MemWrite $end
$var reg 1 , RegDst $end
$var reg 1 + RegWrite $end
$var reg 2 ; pcSrc [1:0] $end
$upscope $end
$scope module data_mem $end
$var wire 1 0 MemWrite $end
$var wire 32 < ReadData [31:0] $end
$var wire 32 = addr [31:0] $end
$var wire 1 " clk $end
$var wire 32 > WriteData [31:0] $end
$upscope $end
$scope module fetch $end
$var wire 32 ? branchAddress [31:0] $end
$var wire 1 " clk $end
$var wire 32 @ pcAtual [31:0] $end
$var wire 2 A pcSrc [1:0] $end
$var wire 1 # reset $end
$var wire 32 B jumpAddress [31:0] $end
$var wire 32 C instrucao [31:0] $end
$var reg 32 D pc [31:0] $end
$scope module mem_inst $end
$var wire 32 E addr [31:0] $end
$var wire 32 F instrucao [31:0] $end
$var integer 32 G i [31:0] $end
$upscope $end
$upscope $end
$scope module jump $end
$var wire 26 H jumpAddr [25:0] $end
$var wire 32 I pcAtual [31:0] $end
$var wire 32 J jumpAddress [31:0] $end
$upscope $end
$scope module regs $end
$var wire 32 K ReadData1 [31:0] $end
$var wire 32 L ReadData2 [31:0] $end
$var wire 5 M ReadRegister1 [4:0] $end
$var wire 5 N ReadRegister2 [4:0] $end
$var wire 1 + RegWrite $end
$var wire 32 O WriteData [31:0] $end
$var wire 5 P WriteRegister [4:0] $end
$var wire 1 " clk $end
$var integer 32 Q i [31:0] $end
$upscope $end
$upscope $end
$upscope $end
$enddefinitions $end
$comment Show the parameter values. $end
$dumpall
$end
#0
$dumpvars
b100000 Q
b1000 P
b0 O
b1000 N
b0 M
b0 L
b0 K
b1000000000000000000100 J
b0 I
b10000000000000000001 H
b100000000 G
b100000000010000000000000000001 F
b0 E
b0 D
b100000000010000000000000000001 C
b1000000000000000000100 B
b0 A
b0 @
b100 ?
b0 >
b0 =
bx <
b0 ;
b0 :
b1000 9
b1 8
b0 7
b0 6
b0 5
b0 4
b0 3
b0 2
01
00
b0 /
b0 .
bx -
0,
0+
b0 *
1)
b100 (
b100000000010000000000000000001 '
b1000000000000000000100 &
b0 %
b0 $
1#
0"
b0 !
$end
#5
1"
#10
0"
0#
#15
b1001 P
b1001000000000000001000 &
b1001000000000000001000 B
b1001000000000000001000 J
b10010000000000000010 H
b10 8
b1001 N
b100000000010010000000000000010 '
b100000000010010000000000000010 C
b100000000010010000000000000010 F
b1100 (
b1100 ?
b100 !
b100 %
b100 @
b100 I
b100 D
b100 E
1"
#20
0"
#25
b1010 P
b10 3
b10 5
b10 :
1,
1+
b100001001010100000010000000 &
b100001001010100000010000000 B
b100001001010100000010000000 J
b1000010010101000000100000 H
b100000 8
b0 9
b1000 M
b1000010010101000000100000 '
b1000010010101000000100000 C
b1000010010101000000100000 F
b10100000010001000 (
b10100000010001000 ?
b1000 !
b1000 %
b1000 @
b1000 I
b1000 D
b1000 E
1"
#30
0"
#35
bx *
bx O
0,
11
10
0+
b1010 P
b1010000000000000000000 &
b1010000000000000000000 B
b1010000000000000000000 J
b10100000000000000000 H
b0 8
b101011 9
b1010 N
b0 M
b10101100000010100000000000000000 '
b10101100000010100000000000000000 C
b10101100000010100000000000000000 F
b1100 (
b1100 ?
b1100 !
b1100 %
b1100 @
b1100 I
b1100 D
b1100 E
1"
#40
0"
#45
b0 3
b0 5
b0 :
1,
01
00
1+
b0 P
b0 &
b0 B
b0 J
b0 H
b0 9
b0 N
b0 *
b0 O
b0 '
b0 C
b0 F
b0 -
b0 <
b10000 (
b10000 ?
b10000 !
b10000 %
b10000 @
b10000 I
b10000 D
b10000 E
1"
#50
0"
#55
b10100 (
b10100 ?
b10100 !
b10100 %
b10100 @
b10100 I
b10100 D
b10100 E
1"
#60
0"
#65
b11000 (
b11000 ?
b11000 !
b11000 %
b11000 @
b11000 I
b11000 D
b11000 E
1"
#70
0"
#75
b11100 (
b11100 ?
b11100 !
b11100 %
b11100 @
b11100 I
b11100 D
b11100 E
1"
#80
0"
#85
b100000 (
b100000 ?
b100000 !
b100000 %
b100000 @
b100000 I
b100000 D
b100000 E
1"
#90
0"
#95
b100100 (
b100100 ?
b100100 !
b100100 %
b100100 @
b100100 I
b100100 D
b100100 E
1"
#100
0"
#105
b101000 (
b101000 ?
b101000 !
b101000 %
b101000 @
b101000 I
b101000 D
b101000 E
1"
